
{"scores":[
  {
    "name":"GerardoA",
    "stroke":"Back",
    "age":"13-14",
    "gender":"Boys",
    "date":"2004-06-12",
    "time":"1:02.31",
    "place":"7",
    "team":"Otters",
    "yards":50,
    "meet":"025",
    "opponent":"Shadowbrook"
  },
  {
    "name":"GerardoA",
    "stroke":"Back",
    "age":"13-14",
    "gender":"Boys",
    "date":"2004-06-26",
    "time":"DQ",
    "place":"--",
    "team":"Otters",
    "yards":50,
    "meet":"027",
    "opponent":"Crossgate"
  },
  {
    "name":"GerardoA",
    "stroke":"Back",
    "age":"13-14",
    "gender":"Boys",
    "date":"2004-07-17",
    "time":"DQ",
    "place":"--",
    "team":"Otters",
    "yards":50,
    "meet":"029",
    "opponent":"Champs"
  },
  {
    "name":"GerardoA",
    "stroke":"Butterfly",
    "age":"13-14",
    "gender":"Boys",
    "date":"2004-06-12",
    "time":"DQ",
    "place":"--",
    "team":"Otters",
    "yards":50,
    "meet":"025",
    "opponent":"Shadowbrook"
  },
  {
    "name":"GerardoA",
    "stroke":"Butterfly",
    "age":"13-14",
    "gender":"Boys",
    "date":"2004-06-19",
    "time":"1:04.60",
    "place":"6",
    "team":"Otters",
    "yards":50,
    "meet":"026",
    "opponent":"Pinehurst"
  },
  {
    "name":"GerardoA",
    "stroke":"Butterfly",
    "age":"13-14",
    "gender":"Boys",
    "date":"2004-06-26",
    "time":"1:07.50",
    "place":"5",
    "team":"Otters",
    "yards":50,
    "meet":"027",
    "opponent":"Crossgate"
  },
  {
    "name":"GerardoA",
    "stroke":"Butterfly",
    "age":"13-14",
    "gender":"Boys",
    "date":"2004-07-10",
    "time":"DQ",
    "place":"--",
    "team":"Otters",
    "yards":50,
    "meet":"028",
    "opponent":"Almaden"
  },
  {
    "name":"GerardoA",
    "stroke":"Butterfly",
    "age":"13-14",
    "gender":"Boys",
    "date":"2004-07-17",
    "time":"DQ",
    "place":"--",
    "team":"Otters",
    "yards":50,
    "meet":"029",
    "opponent":"Champs"
  },
  {
    "name":"GerardoA",
    "stroke":"Freestyle",
    "age":"13-14",
    "gender":"Boys",
    "date":"2004-06-12",
    "time":"45.28",
    "place":"10",
    "team":"Otters",
    "yards":50,
    "meet":"025",
    "opponent":"Shadowbrook"
  },
  {
    "name":"GerardoA",
    "stroke":"Freestyle",
    "age":"13-14",
    "gender":"Boys",
    "date":"2004-06-26",
    "time":"43.25",
    "place":"11",
    "team":"Otters",
    "yards":50,
    "meet":"027",
    "opponent":"Crossgate"
  },
  {
    "name":"GerardoA",
    "stroke":"Freestyle",
    "age":"13-14",
    "gender":"Boys",
    "date":"2004-07-17",
    "time":"39.13",
    "place":"40",
    "team":"Otters",
    "yards":50,
    "meet":"029",
    "opponent":"Champs"
  }
]}


