
{"scores":[
  {
    "name":"AlexanderH",
    "stroke":"Back",
    "age":"11-12",
    "gender":"Boys",
    "date":"2003-05-10",
    "time":"37.27",
    "place":"1",
    "team":"Otters",
    "yards":50,
    "meet":"015",
    "opponent":"Trials"
  },
  {
    "name":"BillP",
    "stroke":"Back",
    "age":"11-12",
    "gender":"Boys",
    "date":"2003-05-10",
    "time":"39.43",
    "place":"2",
    "team":"Otters",
    "yards":50,
    "meet":"015",
    "opponent":"Trials"
  },
  {
    "name":"BramD",
    "stroke":"Back",
    "age":"11-12",
    "gender":"Boys",
    "date":"2003-05-10",
    "time":"41.00",
    "place":"3",
    "team":"Otters",
    "yards":50,
    "meet":"015",
    "opponent":"Trials"
  },
  {
    "name":"RidgeG",
    "stroke":"Back",
    "age":"11-12",
    "gender":"Boys",
    "date":"2003-05-10",
    "time":"43.31",
    "place":"4",
    "team":"Otters",
    "yards":50,
    "meet":"015",
    "opponent":"Trials"
  },
  {
    "name":"ScottD1",
    "stroke":"Back",
    "age":"11-12",
    "gender":"Boys",
    "date":"2003-05-10",
    "time":"50.39",
    "place":"5",
    "team":"Otters",
    "yards":50,
    "meet":"015",
    "opponent":"Trials"
  },
  {
    "name":"KyleB2",
    "stroke":"Back",
    "age":"11-12",
    "gender":"Boys",
    "date":"2003-05-10",
    "time":"59.78",
    "place":"6",
    "team":"Otters",
    "yards":50,
    "meet":"015",
    "opponent":"Trials"
  },
  {
    "name":"ArlaT",
    "stroke":"Back",
    "age":"11-12",
    "gender":"Girls",
    "date":"2003-05-10",
    "time":"36.31",
    "place":"1",
    "team":"Otters",
    "yards":50,
    "meet":"015",
    "opponent":"Trials"
  },
  {
    "name":"ChelseaK",
    "stroke":"Back",
    "age":"11-12",
    "gender":"Girls",
    "date":"2003-05-10",
    "time":"37.49",
    "place":"2",
    "team":"Otters",
    "yards":50,
    "meet":"015",
    "opponent":"Trials"
  },
  {
    "name":"CourtneyK",
    "stroke":"Back",
    "age":"11-12",
    "gender":"Girls",
    "date":"2003-05-10",
    "time":"44.75",
    "place":"3",
    "team":"Otters",
    "yards":50,
    "meet":"015",
    "opponent":"Trials"
  },
  {
    "name":"StefaniS",
    "stroke":"Back",
    "age":"11-12",
    "gender":"Girls",
    "date":"2003-05-10",
    "time":"47.56",
    "place":"4",
    "team":"Otters",
    "yards":50,
    "meet":"015",
    "opponent":"Trials"
  },
  {
    "name":"DeniseD",
    "stroke":"Back",
    "age":"11-12",
    "gender":"Girls",
    "date":"2003-05-10",
    "time":"48.51",
    "place":"5",
    "team":"Otters",
    "yards":50,
    "meet":"015",
    "opponent":"Trials"
  },
  {
    "name":"NicoleT",
    "stroke":"Back",
    "age":"11-12",
    "gender":"Girls",
    "date":"2003-05-10",
    "time":"55.26",
    "place":"6",
    "team":"Otters",
    "yards":50,
    "meet":"015",
    "opponent":"Trials"
  },
  {
    "name":"MeganT",
    "stroke":"Back",
    "age":"11-12",
    "gender":"Girls",
    "date":"2003-05-10",
    "time":"1:07.30",
    "place":"7",
    "team":"Otters",
    "yards":50,
    "meet":"015",
    "opponent":"Trials"
  },
  {
    "name":"AndreaH",
    "stroke":"Back",
    "age":"11-12",
    "gender":"Girls",
    "date":"2003-05-10",
    "time":"1:31.78",
    "place":"8",
    "team":"Otters",
    "yards":50,
    "meet":"015",
    "opponent":"Trials"
  },
  {
    "name":"ChadK",
    "stroke":"Back",
    "age":"13-14",
    "gender":"Boys",
    "date":"2003-05-10",
    "time":"NS",
    "place":"--",
    "team":"Otters",
    "yards":50,
    "meet":"015",
    "opponent":"Trials"
  },
  {
    "name":"TylerT",
    "stroke":"Back",
    "age":"13-14",
    "gender":"Boys",
    "date":"2003-05-10",
    "time":"NS",
    "place":"--",
    "team":"Otters",
    "yards":50,
    "meet":"015",
    "opponent":"Trials"
  },
  {
    "name":"JamesSi",
    "stroke":"Back",
    "age":"13-14",
    "gender":"Boys",
    "date":"2003-05-10",
    "time":"39.73",
    "place":"1",
    "team":"Otters",
    "yards":50,
    "meet":"015",
    "opponent":"Trials"
  },
  {
    "name":"RandyG",
    "stroke":"Back",
    "age":"13-14",
    "gender":"Boys",
    "date":"2003-05-10",
    "time":"40.01",
    "place":"2",
    "team":"Otters",
    "yards":50,
    "meet":"015",
    "opponent":"Trials"
  },
  {
    "name":"SamN",
    "stroke":"Back",
    "age":"13-14",
    "gender":"Boys",
    "date":"2003-05-10",
    "time":"53.13",
    "place":"3",
    "team":"Otters",
    "yards":50,
    "meet":"015",
    "opponent":"Trials"
  },
  {
    "name":"ShainaP",
    "stroke":"Back",
    "age":"13-14",
    "gender":"Girls",
    "date":"2003-05-10",
    "time":"34.98",
    "place":"1",
    "team":"Otters",
    "yards":50,
    "meet":"015",
    "opponent":"Trials"
  },
  {
    "name":"AgathaS",
    "stroke":"Back",
    "age":"13-14",
    "gender":"Girls",
    "date":"2003-05-10",
    "time":"38.37",
    "place":"2",
    "team":"Otters",
    "yards":50,
    "meet":"015",
    "opponent":"Trials"
  },
  {
    "name":"BreannaS",
    "stroke":"Back",
    "age":"13-14",
    "gender":"Girls",
    "date":"2003-05-10",
    "time":"38.53",
    "place":"3",
    "team":"Otters",
    "yards":50,
    "meet":"015",
    "opponent":"Trials"
  },
  {
    "name":"DominicM",
    "stroke":"Back",
    "age":"15-18",
    "gender":"Boys",
    "date":"2003-05-10",
    "time":"NS",
    "place":"--",
    "team":"Otters",
    "yards":50,
    "meet":"015",
    "opponent":"Trials"
  },
  {
    "name":"MaxD",
    "stroke":"Back",
    "age":"15-18",
    "gender":"Boys",
    "date":"2003-05-10",
    "time":"37.72",
    "place":"1",
    "team":"Otters",
    "yards":50,
    "meet":"015",
    "opponent":"Trials"
  },
  {
    "name":"ConnerW",
    "stroke":"Back",
    "age":"15-18",
    "gender":"Boys",
    "date":"2003-05-10",
    "time":"39.99",
    "place":"2",
    "team":"Otters",
    "yards":50,
    "meet":"015",
    "opponent":"Trials"
  },
  {
    "name":"AnnamariaS",
    "stroke":"Back",
    "age":"15-18",
    "gender":"Girls",
    "date":"2003-05-10",
    "time":"37.85",
    "place":"1",
    "team":"Otters",
    "yards":50,
    "meet":"015",
    "opponent":"Trials"
  },
  {
    "name":"JadeG",
    "stroke":"Back",
    "age":"15-18",
    "gender":"Girls",
    "date":"2003-05-10",
    "time":"42.85",
    "place":"2",
    "team":"Otters",
    "yards":50,
    "meet":"015",
    "opponent":"Trials"
  },
  {
    "name":"MathewH2",
    "stroke":"Back",
    "age":"6 & Under",
    "gender":"Boys",
    "date":"2003-05-10",
    "time":"25.38",
    "place":"1",
    "team":"Otters",
    "yards":25,
    "meet":"015",
    "opponent":"Trials"
  },
  {
    "name":"TylerH",
    "stroke":"Back",
    "age":"6 & Under",
    "gender":"Boys",
    "date":"2003-05-10",
    "time":"37.47",
    "place":"2",
    "team":"Otters",
    "yards":25,
    "meet":"015",
    "opponent":"Trials"
  },
  {
    "name":"CoreyG",
    "stroke":"Back",
    "age":"6 & Under",
    "gender":"Boys",
    "date":"2003-05-10",
    "time":"51.89",
    "place":"3",
    "team":"Otters",
    "yards":25,
    "meet":"015",
    "opponent":"Trials"
  },
  {
    "name":"JordanB",
    "stroke":"Back",
    "age":"6 & Under",
    "gender":"Boys",
    "date":"2003-05-10",
    "time":"1:02.00",
    "place":"4",
    "team":"Otters",
    "yards":25,
    "meet":"015",
    "opponent":"Trials"
  },
  {
    "name":"GianaK",
    "stroke":"Back",
    "age":"6 & Under",
    "gender":"Girls",
    "date":"2003-05-10",
    "time":"32.07",
    "place":"1",
    "team":"Otters",
    "yards":25,
    "meet":"015",
    "opponent":"Trials"
  },
  {
    "name":"MarcellaK",
    "stroke":"Back",
    "age":"6 & Under",
    "gender":"Girls",
    "date":"2003-05-10",
    "time":"40.80",
    "place":"2",
    "team":"Otters",
    "yards":25,
    "meet":"015",
    "opponent":"Trials"
  },
  {
    "name":"KasscindraN",
    "stroke":"Back",
    "age":"6 & Under",
    "gender":"Girls",
    "date":"2003-05-10",
    "time":"44.45",
    "place":"3",
    "team":"Otters",
    "yards":25,
    "meet":"015",
    "opponent":"Trials"
  },
  {
    "name":"MiaB",
    "stroke":"Back",
    "age":"6 & Under",
    "gender":"Girls",
    "date":"2003-05-10",
    "time":"47.08",
    "place":"4",
    "team":"Otters",
    "yards":25,
    "meet":"015",
    "opponent":"Trials"
  },
  {
    "name":"EmmaD",
    "stroke":"Back",
    "age":"6 & Under",
    "gender":"Girls",
    "date":"2003-05-10",
    "time":"53.15",
    "place":"5",
    "team":"Otters",
    "yards":25,
    "meet":"015",
    "opponent":"Trials"
  },
  {
    "name":"AllieR",
    "stroke":"Back",
    "age":"6 & Under",
    "gender":"Girls",
    "date":"2003-05-10",
    "time":"55.62",
    "place":"6",
    "team":"Otters",
    "yards":25,
    "meet":"015",
    "opponent":"Trials"
  },
  {
    "name":"RebeccaM",
    "stroke":"Back",
    "age":"6 & Under",
    "gender":"Girls",
    "date":"2003-05-10",
    "time":"1:49.50",
    "place":"7",
    "team":"Otters",
    "yards":25,
    "meet":"015",
    "opponent":"Trials"
  },
  {
    "name":"AlexV",
    "stroke":"Back",
    "age":"7-8",
    "gender":"Boys",
    "date":"2003-05-10",
    "time":"28.52",
    "place":"1",
    "team":"Otters",
    "yards":25,
    "meet":"015",
    "opponent":"Trials"
  },
  {
    "name":"ZacharyN",
    "stroke":"Back",
    "age":"7-8",
    "gender":"Boys",
    "date":"2003-05-10",
    "time":"38.12",
    "place":"2",
    "team":"Otters",
    "yards":25,
    "meet":"015",
    "opponent":"Trials"
  },
  {
    "name":"KyleM",
    "stroke":"Back",
    "age":"7-8",
    "gender":"Boys",
    "date":"2003-05-10",
    "time":"41.44",
    "place":"3",
    "team":"Otters",
    "yards":25,
    "meet":"015",
    "opponent":"Trials"
  },
  {
    "name":"TheresaE",
    "stroke":"Back",
    "age":"7-8",
    "gender":"Girls",
    "date":"2003-05-10",
    "time":"NS",
    "place":"--",
    "team":"Otters",
    "yards":25,
    "meet":"015",
    "opponent":"Trials"
  },
  {
    "name":"AnnaH",
    "stroke":"Back",
    "age":"7-8",
    "gender":"Girls",
    "date":"2003-05-10",
    "time":"23.01",
    "place":"1",
    "team":"Otters",
    "yards":25,
    "meet":"015",
    "opponent":"Trials"
  },
  {
    "name":"EmilyD1",
    "stroke":"Back",
    "age":"7-8",
    "gender":"Girls",
    "date":"2003-05-10",
    "time":"27.35",
    "place":"2",
    "team":"Otters",
    "yards":25,
    "meet":"015",
    "opponent":"Trials"
  },
  {
    "name":"HayleyR",
    "stroke":"Back",
    "age":"7-8",
    "gender":"Girls",
    "date":"2003-05-10",
    "time":"27.59",
    "place":"3",
    "team":"Otters",
    "yards":25,
    "meet":"015",
    "opponent":"Trials"
  },
  {
    "name":"JenniferR",
    "stroke":"Back",
    "age":"7-8",
    "gender":"Girls",
    "date":"2003-05-10",
    "time":"28.50",
    "place":"4",
    "team":"Otters",
    "yards":25,
    "meet":"015",
    "opponent":"Trials"
  },
  {
    "name":"SonyaS",
    "stroke":"Back",
    "age":"7-8",
    "gender":"Girls",
    "date":"2003-05-10",
    "time":"35.87",
    "place":"5",
    "team":"Otters",
    "yards":25,
    "meet":"015",
    "opponent":"Trials"
  },
  {
    "name":"ValerieP",
    "stroke":"Back",
    "age":"7-8",
    "gender":"Girls",
    "date":"2003-05-10",
    "time":"36.24",
    "place":"6",
    "team":"Otters",
    "yards":25,
    "meet":"015",
    "opponent":"Trials"
  },
  {
    "name":"CaitlynB",
    "stroke":"Back",
    "age":"7-8",
    "gender":"Girls",
    "date":"2003-05-10",
    "time":"39.81",
    "place":"7",
    "team":"Otters",
    "yards":25,
    "meet":"015",
    "opponent":"Trials"
  },
  {
    "name":"SereanaR",
    "stroke":"Back",
    "age":"7-8",
    "gender":"Girls",
    "date":"2003-05-10",
    "time":"41.60",
    "place":"8",
    "team":"Otters",
    "yards":25,
    "meet":"015",
    "opponent":"Trials"
  },
  {
    "name":"GiselleH",
    "stroke":"Back",
    "age":"7-8",
    "gender":"Girls",
    "date":"2003-05-10",
    "time":"42.23",
    "place":"9",
    "team":"Otters",
    "yards":25,
    "meet":"015",
    "opponent":"Trials"
  },
  {
    "name":"AustinF",
    "stroke":"Back",
    "age":"9-10",
    "gender":"Boys",
    "date":"2003-05-10",
    "time":"53.10",
    "place":"10",
    "team":"Otters",
    "yards":25,
    "meet":"015",
    "opponent":"Trials"
  },
  {
    "name":"DanteM",
    "stroke":"Back",
    "age":"9-10",
    "gender":"Boys",
    "date":"2003-05-10",
    "time":"22.50",
    "place":"1",
    "team":"Otters",
    "yards":25,
    "meet":"015",
    "opponent":"Trials"
  },
  {
    "name":"ErikV",
    "stroke":"Back",
    "age":"9-10",
    "gender":"Boys",
    "date":"2003-05-10",
    "time":"24.82",
    "place":"2",
    "team":"Otters",
    "yards":25,
    "meet":"015",
    "opponent":"Trials"
  },
  {
    "name":"AlexE",
    "stroke":"Back",
    "age":"9-10",
    "gender":"Boys",
    "date":"2003-05-10",
    "time":"26.25",
    "place":"3",
    "team":"Otters",
    "yards":25,
    "meet":"015",
    "opponent":"Trials"
  },
  {
    "name":"MelkiasG",
    "stroke":"Back",
    "age":"9-10",
    "gender":"Boys",
    "date":"2003-05-10",
    "time":"26.42",
    "place":"4",
    "team":"Otters",
    "yards":25,
    "meet":"015",
    "opponent":"Trials"
  },
  {
    "name":"FernandoR",
    "stroke":"Back",
    "age":"9-10",
    "gender":"Boys",
    "date":"2003-05-10",
    "time":"29.30",
    "place":"5",
    "team":"Otters",
    "yards":25,
    "meet":"015",
    "opponent":"Trials"
  },
  {
    "name":"AlejandroR",
    "stroke":"Back",
    "age":"9-10",
    "gender":"Boys",
    "date":"2003-05-10",
    "time":"29.47",
    "place":"6",
    "team":"Otters",
    "yards":25,
    "meet":"015",
    "opponent":"Trials"
  },
  {
    "name":"AndrewM",
    "stroke":"Back",
    "age":"9-10",
    "gender":"Boys",
    "date":"2003-05-10",
    "time":"34.58",
    "place":"7",
    "team":"Otters",
    "yards":25,
    "meet":"015",
    "opponent":"Trials"
  },
  {
    "name":"JamesR",
    "stroke":"Back",
    "age":"9-10",
    "gender":"Boys",
    "date":"2003-05-10",
    "time":"37.42",
    "place":"8",
    "team":"Otters",
    "yards":25,
    "meet":"015",
    "opponent":"Trials"
  },
  {
    "name":"ChristianH",
    "stroke":"Back",
    "age":"9-10",
    "gender":"Boys",
    "date":"2003-05-10",
    "time":"48.28",
    "place":"9",
    "team":"Otters",
    "yards":25,
    "meet":"015",
    "opponent":"Trials"
  },
  {
    "name":"JessicaS",
    "stroke":"Back",
    "age":"9-10",
    "gender":"Girls",
    "date":"2003-05-10",
    "time":"19.43",
    "place":"1",
    "team":"Otters",
    "yards":25,
    "meet":"015",
    "opponent":"Trials"
  },
  {
    "name":"ElaineH",
    "stroke":"Back",
    "age":"9-10",
    "gender":"Girls",
    "date":"2003-05-10",
    "time":"20.19",
    "place":"2",
    "team":"Otters",
    "yards":25,
    "meet":"015",
    "opponent":"Trials"
  },
  {
    "name":"AishaN",
    "stroke":"Back",
    "age":"9-10",
    "gender":"Girls",
    "date":"2003-05-10",
    "time":"20.27",
    "place":"3",
    "team":"Otters",
    "yards":25,
    "meet":"015",
    "opponent":"Trials"
  },
  {
    "name":"CharlotteS",
    "stroke":"Back",
    "age":"9-10",
    "gender":"Girls",
    "date":"2003-05-10",
    "time":"20.40",
    "place":"4",
    "team":"Otters",
    "yards":25,
    "meet":"015",
    "opponent":"Trials"
  },
  {
    "name":"JamieG",
    "stroke":"Back",
    "age":"9-10",
    "gender":"Girls",
    "date":"2003-05-10",
    "time":"27.15",
    "place":"5",
    "team":"Otters",
    "yards":25,
    "meet":"015",
    "opponent":"Trials"
  },
  {
    "name":"TaylorR",
    "stroke":"Back",
    "age":"9-10",
    "gender":"Girls",
    "date":"2003-05-10",
    "time":"29.50",
    "place":"6",
    "team":"Otters",
    "yards":25,
    "meet":"015",
    "opponent":"Trials"
  },
  {
    "name":"GabrielleC",
    "stroke":"Back",
    "age":"9-10",
    "gender":"Girls",
    "date":"2003-05-10",
    "time":"35.70",
    "place":"7",
    "team":"Otters",
    "yards":25,
    "meet":"015",
    "opponent":"Trials"
  },
  {
    "name":"RidgeG",
    "stroke":"Breast",
    "age":"11-12",
    "gender":"Boys",
    "date":"2003-05-10",
    "time":"NS",
    "place":"--",
    "team":"Otters",
    "yards":50,
    "meet":"015",
    "opponent":"Trials"
  },
  {
    "name":"AlexanderH",
    "stroke":"Breast",
    "age":"11-12",
    "gender":"Boys",
    "date":"2003-05-10",
    "time":"37.72",
    "place":"1",
    "team":"Otters",
    "yards":50,
    "meet":"015",
    "opponent":"Trials"
  },
  {
    "name":"BramD",
    "stroke":"Breast",
    "age":"11-12",
    "gender":"Boys",
    "date":"2003-05-10",
    "time":"39.77",
    "place":"2",
    "team":"Otters",
    "yards":50,
    "meet":"015",
    "opponent":"Trials"
  },
  {
    "name":"BillP",
    "stroke":"Breast",
    "age":"11-12",
    "gender":"Boys",
    "date":"2003-05-10",
    "time":"44.93",
    "place":"3",
    "team":"Otters",
    "yards":50,
    "meet":"015",
    "opponent":"Trials"
  },
  {
    "name":"KyleB2",
    "stroke":"Breast",
    "age":"11-12",
    "gender":"Boys",
    "date":"2003-05-10",
    "time":"54.84",
    "place":"4",
    "team":"Otters",
    "yards":50,
    "meet":"015",
    "opponent":"Trials"
  },
  {
    "name":"ScottD1",
    "stroke":"Breast",
    "age":"11-12",
    "gender":"Boys",
    "date":"2003-05-10",
    "time":"1:12.02",
    "place":"5",
    "team":"Otters",
    "yards":50,
    "meet":"015",
    "opponent":"Trials"
  },
  {
    "name":"ChelseaK",
    "stroke":"Breast",
    "age":"11-12",
    "gender":"Girls",
    "date":"2003-05-10",
    "time":"41.80",
    "place":"1",
    "team":"Otters",
    "yards":50,
    "meet":"015",
    "opponent":"Trials"
  },
  {
    "name":"ArlaT",
    "stroke":"Breast",
    "age":"11-12",
    "gender":"Girls",
    "date":"2003-05-10",
    "time":"43.99",
    "place":"2",
    "team":"Otters",
    "yards":50,
    "meet":"015",
    "opponent":"Trials"
  },
  {
    "name":"DeniseD",
    "stroke":"Breast",
    "age":"11-12",
    "gender":"Girls",
    "date":"2003-05-10",
    "time":"46.08",
    "place":"3",
    "team":"Otters",
    "yards":50,
    "meet":"015",
    "opponent":"Trials"
  },
  {
    "name":"NicoleT",
    "stroke":"Breast",
    "age":"11-12",
    "gender":"Girls",
    "date":"2003-05-10",
    "time":"52.84",
    "place":"4",
    "team":"Otters",
    "yards":50,
    "meet":"015",
    "opponent":"Trials"
  },
  {
    "name":"StefaniS",
    "stroke":"Breast",
    "age":"11-12",
    "gender":"Girls",
    "date":"2003-05-10",
    "time":"53.10",
    "place":"5",
    "team":"Otters",
    "yards":50,
    "meet":"015",
    "opponent":"Trials"
  },
  {
    "name":"CourtneyK",
    "stroke":"Breast",
    "age":"11-12",
    "gender":"Girls",
    "date":"2003-05-10",
    "time":"1:07.60",
    "place":"6",
    "team":"Otters",
    "yards":50,
    "meet":"015",
    "opponent":"Trials"
  },
  {
    "name":"AndreaH",
    "stroke":"Breast",
    "age":"11-12",
    "gender":"Girls",
    "date":"2003-05-10",
    "time":"1:18.03",
    "place":"7",
    "team":"Otters",
    "yards":50,
    "meet":"015",
    "opponent":"Trials"
  },
  {
    "name":"MeganT",
    "stroke":"Breast",
    "age":"11-12",
    "gender":"Girls",
    "date":"2003-05-10",
    "time":"1:28.43",
    "place":"8",
    "team":"Otters",
    "yards":50,
    "meet":"015",
    "opponent":"Trials"
  },
  {
    "name":"ChadK",
    "stroke":"Breast",
    "age":"13-14",
    "gender":"Boys",
    "date":"2003-05-10",
    "time":"NS",
    "place":"--",
    "team":"Otters",
    "yards":50,
    "meet":"015",
    "opponent":"Trials"
  },
  {
    "name":"RandyG",
    "stroke":"Breast",
    "age":"13-14",
    "gender":"Boys",
    "date":"2003-05-10",
    "time":"NS",
    "place":"--",
    "team":"Otters",
    "yards":50,
    "meet":"015",
    "opponent":"Trials"
  },
  {
    "name":"TylerT",
    "stroke":"Breast",
    "age":"13-14",
    "gender":"Boys",
    "date":"2003-05-10",
    "time":"NS",
    "place":"--",
    "team":"Otters",
    "yards":50,
    "meet":"015",
    "opponent":"Trials"
  },
  {
    "name":"JamesSi",
    "stroke":"Breast",
    "age":"13-14",
    "gender":"Boys",
    "date":"2003-05-10",
    "time":"43.40",
    "place":"1",
    "team":"Otters",
    "yards":50,
    "meet":"015",
    "opponent":"Trials"
  },
  {
    "name":"SamN",
    "stroke":"Breast",
    "age":"13-14",
    "gender":"Boys",
    "date":"2003-05-10",
    "time":"53.58",
    "place":"2",
    "team":"Otters",
    "yards":50,
    "meet":"015",
    "opponent":"Trials"
  },
  {
    "name":"AgathaS",
    "stroke":"Breast",
    "age":"13-14",
    "gender":"Girls",
    "date":"2003-05-10",
    "time":"40.10",
    "place":"1",
    "team":"Otters",
    "yards":50,
    "meet":"015",
    "opponent":"Trials"
  },
  {
    "name":"ShainaP",
    "stroke":"Breast",
    "age":"13-14",
    "gender":"Girls",
    "date":"2003-05-10",
    "time":"41.64",
    "place":"2",
    "team":"Otters",
    "yards":50,
    "meet":"015",
    "opponent":"Trials"
  },
  {
    "name":"BreannaS",
    "stroke":"Breast",
    "age":"13-14",
    "gender":"Girls",
    "date":"2003-05-10",
    "time":"44.81",
    "place":"3",
    "team":"Otters",
    "yards":50,
    "meet":"015",
    "opponent":"Trials"
  },
  {
    "name":"DominicM",
    "stroke":"Breast",
    "age":"15-18",
    "gender":"Boys",
    "date":"2003-05-10",
    "time":"NS",
    "place":"--",
    "team":"Otters",
    "yards":50,
    "meet":"015",
    "opponent":"Trials"
  },
  {
    "name":"MaxD",
    "stroke":"Breast",
    "age":"15-18",
    "gender":"Boys",
    "date":"2003-05-10",
    "time":"39.91",
    "place":"1",
    "team":"Otters",
    "yards":50,
    "meet":"015",
    "opponent":"Trials"
  },
  {
    "name":"ConnerW",
    "stroke":"Breast",
    "age":"15-18",
    "gender":"Boys",
    "date":"2003-05-10",
    "time":"40.24",
    "place":"2",
    "team":"Otters",
    "yards":50,
    "meet":"015",
    "opponent":"Trials"
  },
  {
    "name":"JadeG",
    "stroke":"Breast",
    "age":"15-18",
    "gender":"Girls",
    "date":"2003-05-10",
    "time":"42.82",
    "place":"1",
    "team":"Otters",
    "yards":50,
    "meet":"015",
    "opponent":"Trials"
  },
  {
    "name":"AnnamariaS",
    "stroke":"Breast",
    "age":"15-18",
    "gender":"Girls",
    "date":"2003-05-10",
    "time":"43.82",
    "place":"2",
    "team":"Otters",
    "yards":50,
    "meet":"015",
    "opponent":"Trials"
  },
  {
    "name":"MathewH2",
    "stroke":"Breast",
    "age":"8 & Under",
    "gender":"Boys",
    "date":"2003-05-10",
    "time":"30.80",
    "place":"1",
    "team":"Otters",
    "yards":25,
    "meet":"015",
    "opponent":"Trials"
  },
  {
    "name":"AlexV",
    "stroke":"Breast",
    "age":"8 & Under",
    "gender":"Boys",
    "date":"2003-05-10",
    "time":"36.20",
    "place":"2",
    "team":"Otters",
    "yards":25,
    "meet":"015",
    "opponent":"Trials"
  },
  {
    "name":"ZacharyN",
    "stroke":"Breast",
    "age":"8 & Under",
    "gender":"Boys",
    "date":"2003-05-10",
    "time":"38.38",
    "place":"3",
    "team":"Otters",
    "yards":25,
    "meet":"015",
    "opponent":"Trials"
  },
  {
    "name":"KyleM",
    "stroke":"Breast",
    "age":"8 & Under",
    "gender":"Boys",
    "date":"2003-05-10",
    "time":"38.57",
    "place":"4",
    "team":"Otters",
    "yards":25,
    "meet":"015",
    "opponent":"Trials"
  },
  {
    "name":"EmmaD",
    "stroke":"Breast",
    "age":"8 & Under",
    "gender":"Girls",
    "date":"2003-05-10",
    "time":"NS",
    "place":"--",
    "team":"Otters",
    "yards":25,
    "meet":"015",
    "opponent":"Trials"
  },
  {
    "name":"GianaK",
    "stroke":"Breast",
    "age":"8 & Under",
    "gender":"Girls",
    "date":"2003-05-10",
    "time":"NS",
    "place":"--",
    "team":"Otters",
    "yards":25,
    "meet":"015",
    "opponent":"Trials"
  },
  {
    "name":"TheresaE",
    "stroke":"Breast",
    "age":"8 & Under",
    "gender":"Girls",
    "date":"2003-05-10",
    "time":"NS",
    "place":"--",
    "team":"Otters",
    "yards":25,
    "meet":"015",
    "opponent":"Trials"
  },
  {
    "name":"GiselleH",
    "stroke":"Breast",
    "age":"8 & Under",
    "gender":"Girls",
    "date":"2003-05-10",
    "time":"55.00",
    "place":"10",
    "team":"Otters",
    "yards":25,
    "meet":"015",
    "opponent":"Trials"
  },
  {
    "name":"AnnaH",
    "stroke":"Breast",
    "age":"8 & Under",
    "gender":"Girls",
    "date":"2003-05-10",
    "time":"24.92",
    "place":"1",
    "team":"Otters",
    "yards":25,
    "meet":"015",
    "opponent":"Trials"
  },
  {
    "name":"CaitlynB",
    "stroke":"Breast",
    "age":"8 & Under",
    "gender":"Girls",
    "date":"2003-05-10",
    "time":"32.97",
    "place":"2",
    "team":"Otters",
    "yards":25,
    "meet":"015",
    "opponent":"Trials"
  },
  {
    "name":"MarcellaK",
    "stroke":"Breast",
    "age":"8 & Under",
    "gender":"Girls",
    "date":"2003-05-10",
    "time":"35.68",
    "place":"3",
    "team":"Otters",
    "yards":25,
    "meet":"015",
    "opponent":"Trials"
  },
  {
    "name":"JenniferR",
    "stroke":"Breast",
    "age":"8 & Under",
    "gender":"Girls",
    "date":"2003-05-10",
    "time":"37.93",
    "place":"4",
    "team":"Otters",
    "yards":25,
    "meet":"015",
    "opponent":"Trials"
  },
  {
    "name":"SonyaS",
    "stroke":"Breast",
    "age":"8 & Under",
    "gender":"Girls",
    "date":"2003-05-10",
    "time":"38.74",
    "place":"5",
    "team":"Otters",
    "yards":25,
    "meet":"015",
    "opponent":"Trials"
  },
  {
    "name":"ValerieP",
    "stroke":"Breast",
    "age":"8 & Under",
    "gender":"Girls",
    "date":"2003-05-10",
    "time":"39.60",
    "place":"6",
    "team":"Otters",
    "yards":25,
    "meet":"015",
    "opponent":"Trials"
  },
  {
    "name":"HayleyR",
    "stroke":"Breast",
    "age":"8 & Under",
    "gender":"Girls",
    "date":"2003-05-10",
    "time":"44.80",
    "place":"7",
    "team":"Otters",
    "yards":25,
    "meet":"015",
    "opponent":"Trials"
  },
  {
    "name":"EmilyD1",
    "stroke":"Breast",
    "age":"8 & Under",
    "gender":"Girls",
    "date":"2003-05-10",
    "time":"47.52",
    "place":"8",
    "team":"Otters",
    "yards":25,
    "meet":"015",
    "opponent":"Trials"
  },
  {
    "name":"SereanaR",
    "stroke":"Breast",
    "age":"8 & Under",
    "gender":"Girls",
    "date":"2003-05-10",
    "time":"51.41",
    "place":"9",
    "team":"Otters",
    "yards":25,
    "meet":"015",
    "opponent":"Trials"
  },
  {
    "name":"DanteM",
    "stroke":"Breast",
    "age":"9-10",
    "gender":"Boys",
    "date":"2003-05-10",
    "time":"NS",
    "place":"--",
    "team":"Otters",
    "yards":25,
    "meet":"015",
    "opponent":"Trials"
  },
  {
    "name":"ErikV",
    "stroke":"Breast",
    "age":"9-10",
    "gender":"Boys",
    "date":"2003-05-10",
    "time":"23.41",
    "place":"1",
    "team":"Otters",
    "yards":25,
    "meet":"015",
    "opponent":"Trials"
  },
  {
    "name":"FernandoR",
    "stroke":"Breast",
    "age":"9-10",
    "gender":"Boys",
    "date":"2003-05-10",
    "time":"30.84",
    "place":"2",
    "team":"Otters",
    "yards":25,
    "meet":"015",
    "opponent":"Trials"
  },
  {
    "name":"JamesR",
    "stroke":"Breast",
    "age":"9-10",
    "gender":"Boys",
    "date":"2003-05-10",
    "time":"33.86",
    "place":"3",
    "team":"Otters",
    "yards":25,
    "meet":"015",
    "opponent":"Trials"
  },
  {
    "name":"AustinF",
    "stroke":"Breast",
    "age":"9-10",
    "gender":"Boys",
    "date":"2003-05-10",
    "time":"33.96",
    "place":"4",
    "team":"Otters",
    "yards":25,
    "meet":"015",
    "opponent":"Trials"
  },
  {
    "name":"AlejandroR",
    "stroke":"Breast",
    "age":"9-10",
    "gender":"Boys",
    "date":"2003-05-10",
    "time":"37.30",
    "place":"5",
    "team":"Otters",
    "yards":25,
    "meet":"015",
    "opponent":"Trials"
  },
  {
    "name":"AndrewM",
    "stroke":"Breast",
    "age":"9-10",
    "gender":"Boys",
    "date":"2003-05-10",
    "time":"38.82",
    "place":"6",
    "team":"Otters",
    "yards":25,
    "meet":"015",
    "opponent":"Trials"
  },
  {
    "name":"MelkiasG",
    "stroke":"Breast",
    "age":"9-10",
    "gender":"Boys",
    "date":"2003-05-10",
    "time":"41.17",
    "place":"7",
    "team":"Otters",
    "yards":25,
    "meet":"015",
    "opponent":"Trials"
  },
  {
    "name":"AlexE",
    "stroke":"Breast",
    "age":"9-10",
    "gender":"Boys",
    "date":"2003-05-10",
    "time":"43.47",
    "place":"8",
    "team":"Otters",
    "yards":25,
    "meet":"015",
    "opponent":"Trials"
  },
  {
    "name":"ChristianH",
    "stroke":"Breast",
    "age":"9-10",
    "gender":"Boys",
    "date":"2003-05-10",
    "time":"52.37",
    "place":"9",
    "team":"Otters",
    "yards":25,
    "meet":"015",
    "opponent":"Trials"
  },
  {
    "name":"ElaineH",
    "stroke":"Breast",
    "age":"9-10",
    "gender":"Girls",
    "date":"2003-05-10",
    "time":"21.43",
    "place":"1",
    "team":"Otters",
    "yards":25,
    "meet":"015",
    "opponent":"Trials"
  },
  {
    "name":"AishaN",
    "stroke":"Breast",
    "age":"9-10",
    "gender":"Girls",
    "date":"2003-05-10",
    "time":"22.19",
    "place":"2",
    "team":"Otters",
    "yards":25,
    "meet":"015",
    "opponent":"Trials"
  },
  {
    "name":"JessicaS",
    "stroke":"Breast",
    "age":"9-10",
    "gender":"Girls",
    "date":"2003-05-10",
    "time":"22.90",
    "place":"3",
    "team":"Otters",
    "yards":25,
    "meet":"015",
    "opponent":"Trials"
  },
  {
    "name":"CharlotteS",
    "stroke":"Breast",
    "age":"9-10",
    "gender":"Girls",
    "date":"2003-05-10",
    "time":"23.56",
    "place":"4",
    "team":"Otters",
    "yards":25,
    "meet":"015",
    "opponent":"Trials"
  },
  {
    "name":"JamieG",
    "stroke":"Breast",
    "age":"9-10",
    "gender":"Girls",
    "date":"2003-05-10",
    "time":"24.69",
    "place":"5",
    "team":"Otters",
    "yards":25,
    "meet":"015",
    "opponent":"Trials"
  },
  {
    "name":"TaylorR",
    "stroke":"Breast",
    "age":"9-10",
    "gender":"Girls",
    "date":"2003-05-10",
    "time":"31.44",
    "place":"6",
    "team":"Otters",
    "yards":25,
    "meet":"015",
    "opponent":"Trials"
  },
  {
    "name":"GabrielleC",
    "stroke":"Breast",
    "age":"9-10",
    "gender":"Girls",
    "date":"2003-05-10",
    "time":"43.43",
    "place":"7",
    "team":"Otters",
    "yards":25,
    "meet":"015",
    "opponent":"Trials"
  },
  {
    "name":"AlexanderH",
    "stroke":"Butterfly",
    "age":"11-12",
    "gender":"Boys",
    "date":"2003-05-10",
    "time":"34.03",
    "place":"1",
    "team":"Otters",
    "yards":50,
    "meet":"015",
    "opponent":"Trials"
  },
  {
    "name":"BillP",
    "stroke":"Butterfly",
    "age":"11-12",
    "gender":"Boys",
    "date":"2003-05-10",
    "time":"35.60",
    "place":"2",
    "team":"Otters",
    "yards":50,
    "meet":"015",
    "opponent":"Trials"
  },
  {
    "name":"BramD",
    "stroke":"Butterfly",
    "age":"11-12",
    "gender":"Boys",
    "date":"2003-05-10",
    "time":"37.00",
    "place":"3",
    "team":"Otters",
    "yards":50,
    "meet":"015",
    "opponent":"Trials"
  },
  {
    "name":"RidgeG",
    "stroke":"Butterfly",
    "age":"11-12",
    "gender":"Boys",
    "date":"2003-05-10",
    "time":"42.21",
    "place":"4",
    "team":"Otters",
    "yards":50,
    "meet":"015",
    "opponent":"Trials"
  },
  {
    "name":"KyleB2",
    "stroke":"Butterfly",
    "age":"11-12",
    "gender":"Boys",
    "date":"2003-05-10",
    "time":"55.06",
    "place":"5",
    "team":"Otters",
    "yards":50,
    "meet":"015",
    "opponent":"Trials"
  },
  {
    "name":"ScottD1",
    "stroke":"Butterfly",
    "age":"11-12",
    "gender":"Boys",
    "date":"2003-05-10",
    "time":"1:03.00",
    "place":"6",
    "team":"Otters",
    "yards":50,
    "meet":"015",
    "opponent":"Trials"
  },
  {
    "name":"ArlaT",
    "stroke":"Butterfly",
    "age":"11-12",
    "gender":"Girls",
    "date":"2003-05-10",
    "time":"33.62",
    "place":"1",
    "team":"Otters",
    "yards":50,
    "meet":"015",
    "opponent":"Trials"
  },
  {
    "name":"ChelseaK",
    "stroke":"Butterfly",
    "age":"11-12",
    "gender":"Girls",
    "date":"2003-05-10",
    "time":"37.00",
    "place":"2",
    "team":"Otters",
    "yards":50,
    "meet":"015",
    "opponent":"Trials"
  },
  {
    "name":"NicoleT",
    "stroke":"Butterfly",
    "age":"11-12",
    "gender":"Girls",
    "date":"2003-05-10",
    "time":"46.12",
    "place":"3",
    "team":"Otters",
    "yards":50,
    "meet":"015",
    "opponent":"Trials"
  },
  {
    "name":"DeniseD",
    "stroke":"Butterfly",
    "age":"11-12",
    "gender":"Girls",
    "date":"2003-05-10",
    "time":"47.27",
    "place":"4",
    "team":"Otters",
    "yards":50,
    "meet":"015",
    "opponent":"Trials"
  },
  {
    "name":"StefaniS",
    "stroke":"Butterfly",
    "age":"11-12",
    "gender":"Girls",
    "date":"2003-05-10",
    "time":"50.15",
    "place":"5",
    "team":"Otters",
    "yards":50,
    "meet":"015",
    "opponent":"Trials"
  },
  {
    "name":"CourtneyK",
    "stroke":"Butterfly",
    "age":"11-12",
    "gender":"Girls",
    "date":"2003-05-10",
    "time":"55.69",
    "place":"6",
    "team":"Otters",
    "yards":50,
    "meet":"015",
    "opponent":"Trials"
  },
  {
    "name":"MeganT",
    "stroke":"Butterfly",
    "age":"11-12",
    "gender":"Girls",
    "date":"2003-05-10",
    "time":"1:09.35",
    "place":"7",
    "team":"Otters",
    "yards":50,
    "meet":"015",
    "opponent":"Trials"
  },
  {
    "name":"AndreaH",
    "stroke":"Butterfly",
    "age":"11-12",
    "gender":"Girls",
    "date":"2003-05-10",
    "time":"1:30.55",
    "place":"8",
    "team":"Otters",
    "yards":50,
    "meet":"015",
    "opponent":"Trials"
  },
  {
    "name":"ChadK",
    "stroke":"Butterfly",
    "age":"13-14",
    "gender":"Boys",
    "date":"2003-05-10",
    "time":"29.10",
    "place":"1",
    "team":"Otters",
    "yards":50,
    "meet":"015",
    "opponent":"Trials"
  },
  {
    "name":"TylerT",
    "stroke":"Butterfly",
    "age":"13-14",
    "gender":"Boys",
    "date":"2003-05-10",
    "time":"30.50",
    "place":"2",
    "team":"Otters",
    "yards":50,
    "meet":"015",
    "opponent":"Trials"
  },
  {
    "name":"JamesSi",
    "stroke":"Butterfly",
    "age":"13-14",
    "gender":"Boys",
    "date":"2003-05-10",
    "time":"36.30",
    "place":"3",
    "team":"Otters",
    "yards":50,
    "meet":"015",
    "opponent":"Trials"
  },
  {
    "name":"RandyG",
    "stroke":"Butterfly",
    "age":"13-14",
    "gender":"Boys",
    "date":"2003-05-10",
    "time":"38.88",
    "place":"4",
    "team":"Otters",
    "yards":50,
    "meet":"015",
    "opponent":"Trials"
  },
  {
    "name":"SamN",
    "stroke":"Butterfly",
    "age":"13-14",
    "gender":"Boys",
    "date":"2003-05-10",
    "time":"50.73",
    "place":"5",
    "team":"Otters",
    "yards":50,
    "meet":"015",
    "opponent":"Trials"
  },
  {
    "name":"ShainaP",
    "stroke":"Butterfly",
    "age":"13-14",
    "gender":"Girls",
    "date":"2003-05-10",
    "time":"34.42",
    "place":"1",
    "team":"Otters",
    "yards":50,
    "meet":"015",
    "opponent":"Trials"
  },
  {
    "name":"BreannaS",
    "stroke":"Butterfly",
    "age":"13-14",
    "gender":"Girls",
    "date":"2003-05-10",
    "time":"35.29",
    "place":"2",
    "team":"Otters",
    "yards":50,
    "meet":"015",
    "opponent":"Trials"
  },
  {
    "name":"AgathaS",
    "stroke":"Butterfly",
    "age":"13-14",
    "gender":"Girls",
    "date":"2003-05-10",
    "time":"37.78",
    "place":"3",
    "team":"Otters",
    "yards":50,
    "meet":"015",
    "opponent":"Trials"
  },
  {
    "name":"DominicM",
    "stroke":"Butterfly",
    "age":"15-18",
    "gender":"Boys",
    "date":"2003-05-10",
    "time":"26.23",
    "place":"1",
    "team":"Otters",
    "yards":50,
    "meet":"015",
    "opponent":"Trials"
  },
  {
    "name":"ConnerW",
    "stroke":"Butterfly",
    "age":"15-18",
    "gender":"Boys",
    "date":"2003-05-10",
    "time":"36.49",
    "place":"2",
    "team":"Otters",
    "yards":50,
    "meet":"015",
    "opponent":"Trials"
  },
  {
    "name":"MaxD",
    "stroke":"Butterfly",
    "age":"15-18",
    "gender":"Boys",
    "date":"2003-05-10",
    "time":"37.04",
    "place":"3",
    "team":"Otters",
    "yards":50,
    "meet":"015",
    "opponent":"Trials"
  },
  {
    "name":"JadeG",
    "stroke":"Butterfly",
    "age":"15-18",
    "gender":"Girls",
    "date":"2003-05-10",
    "time":"NS",
    "place":"--",
    "team":"Otters",
    "yards":50,
    "meet":"015",
    "opponent":"Trials"
  },
  {
    "name":"AnnamariaS",
    "stroke":"Butterfly",
    "age":"15-18",
    "gender":"Girls",
    "date":"2003-05-10",
    "time":"35.40",
    "place":"1",
    "team":"Otters",
    "yards":50,
    "meet":"015",
    "opponent":"Trials"
  },
  {
    "name":"MathewH2",
    "stroke":"Butterfly",
    "age":"8 & Under",
    "gender":"Boys",
    "date":"2003-05-10",
    "time":"23.29",
    "place":"1",
    "team":"Otters",
    "yards":25,
    "meet":"015",
    "opponent":"Trials"
  },
  {
    "name":"AlexV",
    "stroke":"Butterfly",
    "age":"8 & Under",
    "gender":"Boys",
    "date":"2003-05-10",
    "time":"27.35",
    "place":"2",
    "team":"Otters",
    "yards":25,
    "meet":"015",
    "opponent":"Trials"
  },
  {
    "name":"ZacharyN",
    "stroke":"Butterfly",
    "age":"8 & Under",
    "gender":"Boys",
    "date":"2003-05-10",
    "time":"29.25",
    "place":"3",
    "team":"Otters",
    "yards":25,
    "meet":"015",
    "opponent":"Trials"
  },
  {
    "name":"KyleM",
    "stroke":"Butterfly",
    "age":"8 & Under",
    "gender":"Boys",
    "date":"2003-05-10",
    "time":"33.53",
    "place":"4",
    "team":"Otters",
    "yards":25,
    "meet":"015",
    "opponent":"Trials"
  },
  {
    "name":"EmilyD1",
    "stroke":"Butterfly",
    "age":"8 & Under",
    "gender":"Girls",
    "date":"2003-05-10",
    "time":"NS",
    "place":"--",
    "team":"Otters",
    "yards":25,
    "meet":"015",
    "opponent":"Trials"
  },
  {
    "name":"EmmaD",
    "stroke":"Butterfly",
    "age":"8 & Under",
    "gender":"Girls",
    "date":"2003-05-10",
    "time":"NS",
    "place":"--",
    "team":"Otters",
    "yards":25,
    "meet":"015",
    "opponent":"Trials"
  },
  {
    "name":"GianaK",
    "stroke":"Butterfly",
    "age":"8 & Under",
    "gender":"Girls",
    "date":"2003-05-10",
    "time":"NS",
    "place":"--",
    "team":"Otters",
    "yards":25,
    "meet":"015",
    "opponent":"Trials"
  },
  {
    "name":"MarcellaK",
    "stroke":"Butterfly",
    "age":"8 & Under",
    "gender":"Girls",
    "date":"2003-05-10",
    "time":"NS",
    "place":"--",
    "team":"Otters",
    "yards":25,
    "meet":"015",
    "opponent":"Trials"
  },
  {
    "name":"TheresaE",
    "stroke":"Butterfly",
    "age":"8 & Under",
    "gender":"Girls",
    "date":"2003-05-10",
    "time":"NS",
    "place":"--",
    "team":"Otters",
    "yards":25,
    "meet":"015",
    "opponent":"Trials"
  },
  {
    "name":"AnnaH",
    "stroke":"Butterfly",
    "age":"8 & Under",
    "gender":"Girls",
    "date":"2003-05-10",
    "time":"17.49",
    "place":"1",
    "team":"Otters",
    "yards":25,
    "meet":"015",
    "opponent":"Trials"
  },
  {
    "name":"JenniferR",
    "stroke":"Butterfly",
    "age":"8 & Under",
    "gender":"Girls",
    "date":"2003-05-10",
    "time":"31.97",
    "place":"2",
    "team":"Otters",
    "yards":25,
    "meet":"015",
    "opponent":"Trials"
  },
  {
    "name":"HayleyR",
    "stroke":"Butterfly",
    "age":"8 & Under",
    "gender":"Girls",
    "date":"2003-05-10",
    "time":"36.46",
    "place":"3",
    "team":"Otters",
    "yards":25,
    "meet":"015",
    "opponent":"Trials"
  },
  {
    "name":"SonyaS",
    "stroke":"Butterfly",
    "age":"8 & Under",
    "gender":"Girls",
    "date":"2003-05-10",
    "time":"39.10",
    "place":"4",
    "team":"Otters",
    "yards":25,
    "meet":"015",
    "opponent":"Trials"
  },
  {
    "name":"SereanaR",
    "stroke":"Butterfly",
    "age":"8 & Under",
    "gender":"Girls",
    "date":"2003-05-10",
    "time":"41.85",
    "place":"5",
    "team":"Otters",
    "yards":25,
    "meet":"015",
    "opponent":"Trials"
  },
  {
    "name":"GiselleH",
    "stroke":"Butterfly",
    "age":"8 & Under",
    "gender":"Girls",
    "date":"2003-05-10",
    "time":"42.49",
    "place":"6",
    "team":"Otters",
    "yards":25,
    "meet":"015",
    "opponent":"Trials"
  },
  {
    "name":"CaitlynB",
    "stroke":"Butterfly",
    "age":"8 & Under",
    "gender":"Girls",
    "date":"2003-05-10",
    "time":"42.83",
    "place":"7",
    "team":"Otters",
    "yards":25,
    "meet":"015",
    "opponent":"Trials"
  },
  {
    "name":"ValerieP",
    "stroke":"Butterfly",
    "age":"8 & Under",
    "gender":"Girls",
    "date":"2003-05-10",
    "time":"47.30",
    "place":"8",
    "team":"Otters",
    "yards":25,
    "meet":"015",
    "opponent":"Trials"
  },
  {
    "name":"AustinF",
    "stroke":"Butterfly",
    "age":"9-10",
    "gender":"Boys",
    "date":"2003-05-10",
    "time":"42.83",
    "place":"10",
    "team":"Otters",
    "yards":25,
    "meet":"015",
    "opponent":"Trials"
  },
  {
    "name":"DanteM",
    "stroke":"Butterfly",
    "age":"9-10",
    "gender":"Boys",
    "date":"2003-05-10",
    "time":"20.01",
    "place":"1",
    "team":"Otters",
    "yards":25,
    "meet":"015",
    "opponent":"Trials"
  },
  {
    "name":"ErikV",
    "stroke":"Butterfly",
    "age":"9-10",
    "gender":"Boys",
    "date":"2003-05-10",
    "time":"21.50",
    "place":"2",
    "team":"Otters",
    "yards":25,
    "meet":"015",
    "opponent":"Trials"
  },
  {
    "name":"MelkiasG",
    "stroke":"Butterfly",
    "age":"9-10",
    "gender":"Boys",
    "date":"2003-05-10",
    "time":"26.45",
    "place":"3",
    "team":"Otters",
    "yards":25,
    "meet":"015",
    "opponent":"Trials"
  },
  {
    "name":"JamesR",
    "stroke":"Butterfly",
    "age":"9-10",
    "gender":"Boys",
    "date":"2003-05-10",
    "time":"28.21",
    "place":"4",
    "team":"Otters",
    "yards":25,
    "meet":"015",
    "opponent":"Trials"
  },
  {
    "name":"FernandoR",
    "stroke":"Butterfly",
    "age":"9-10",
    "gender":"Boys",
    "date":"2003-05-10",
    "time":"30.58",
    "place":"5",
    "team":"Otters",
    "yards":25,
    "meet":"015",
    "opponent":"Trials"
  },
  {
    "name":"AlexE",
    "stroke":"Butterfly",
    "age":"9-10",
    "gender":"Boys",
    "date":"2003-05-10",
    "time":"32.57",
    "place":"6",
    "team":"Otters",
    "yards":25,
    "meet":"015",
    "opponent":"Trials"
  },
  {
    "name":"AlejandroR",
    "stroke":"Butterfly",
    "age":"9-10",
    "gender":"Boys",
    "date":"2003-05-10",
    "time":"33.29",
    "place":"7",
    "team":"Otters",
    "yards":25,
    "meet":"015",
    "opponent":"Trials"
  },
  {
    "name":"AndrewM",
    "stroke":"Butterfly",
    "age":"9-10",
    "gender":"Boys",
    "date":"2003-05-10",
    "time":"35.92",
    "place":"8",
    "team":"Otters",
    "yards":25,
    "meet":"015",
    "opponent":"Trials"
  },
  {
    "name":"ChristianH",
    "stroke":"Butterfly",
    "age":"9-10",
    "gender":"Boys",
    "date":"2003-05-10",
    "time":"39.90",
    "place":"9",
    "team":"Otters",
    "yards":25,
    "meet":"015",
    "opponent":"Trials"
  },
  {
    "name":"ElaineH",
    "stroke":"Butterfly",
    "age":"9-10",
    "gender":"Girls",
    "date":"2003-05-10",
    "time":"16.44",
    "place":"1",
    "team":"Otters",
    "yards":25,
    "meet":"015",
    "opponent":"Trials"
  },
  {
    "name":"JessicaS",
    "stroke":"Butterfly",
    "age":"9-10",
    "gender":"Girls",
    "date":"2003-05-10",
    "time":"17.74",
    "place":"2",
    "team":"Otters",
    "yards":25,
    "meet":"015",
    "opponent":"Trials"
  },
  {
    "name":"AishaN",
    "stroke":"Butterfly",
    "age":"9-10",
    "gender":"Girls",
    "date":"2003-05-10",
    "time":"18.34",
    "place":"3",
    "team":"Otters",
    "yards":25,
    "meet":"015",
    "opponent":"Trials"
  },
  {
    "name":"CharlotteS",
    "stroke":"Butterfly",
    "age":"9-10",
    "gender":"Girls",
    "date":"2003-05-10",
    "time":"21.67",
    "place":"4",
    "team":"Otters",
    "yards":25,
    "meet":"015",
    "opponent":"Trials"
  },
  {
    "name":"JamieG",
    "stroke":"Butterfly",
    "age":"9-10",
    "gender":"Girls",
    "date":"2003-05-10",
    "time":"23.23",
    "place":"5",
    "team":"Otters",
    "yards":25,
    "meet":"015",
    "opponent":"Trials"
  },
  {
    "name":"TaylorR",
    "stroke":"Butterfly",
    "age":"9-10",
    "gender":"Girls",
    "date":"2003-05-10",
    "time":"33.84",
    "place":"6",
    "team":"Otters",
    "yards":25,
    "meet":"015",
    "opponent":"Trials"
  },
  {
    "name":"GabrielleC",
    "stroke":"Butterfly",
    "age":"9-10",
    "gender":"Girls",
    "date":"2003-05-10",
    "time":"35.01",
    "place":"7",
    "team":"Otters",
    "yards":25,
    "meet":"015",
    "opponent":"Trials"
  },
  {
    "name":"RidgeG",
    "stroke":"Freestyle",
    "age":"11-12",
    "gender":"Boys",
    "date":"2003-05-10",
    "time":"NS",
    "place":"--",
    "team":"Otters",
    "yards":50,
    "meet":"015",
    "opponent":"Trials"
  },
  {
    "name":"AlexanderH",
    "stroke":"Freestyle",
    "age":"11-12",
    "gender":"Boys",
    "date":"2003-05-10",
    "time":"27.64",
    "place":"1",
    "team":"Otters",
    "yards":50,
    "meet":"015",
    "opponent":"Trials"
  },
  {
    "name":"BillP",
    "stroke":"Freestyle",
    "age":"11-12",
    "gender":"Boys",
    "date":"2003-05-10",
    "time":"31.52",
    "place":"2",
    "team":"Otters",
    "yards":50,
    "meet":"015",
    "opponent":"Trials"
  },
  {
    "name":"BramD",
    "stroke":"Freestyle",
    "age":"11-12",
    "gender":"Boys",
    "date":"2003-05-10",
    "time":"33.05",
    "place":"3",
    "team":"Otters",
    "yards":50,
    "meet":"015",
    "opponent":"Trials"
  },
  {
    "name":"ScottD1",
    "stroke":"Freestyle",
    "age":"11-12",
    "gender":"Boys",
    "date":"2003-05-10",
    "time":"43.01",
    "place":"4",
    "team":"Otters",
    "yards":50,
    "meet":"015",
    "opponent":"Trials"
  },
  {
    "name":"KyleB2",
    "stroke":"Freestyle",
    "age":"11-12",
    "gender":"Boys",
    "date":"2003-05-10",
    "time":"46.85",
    "place":"5",
    "team":"Otters",
    "yards":50,
    "meet":"015",
    "opponent":"Trials"
  },
  {
    "name":"ArlaT",
    "stroke":"Freestyle",
    "age":"11-12",
    "gender":"Girls",
    "date":"2003-05-10",
    "time":"29.19",
    "place":"1",
    "team":"Otters",
    "yards":50,
    "meet":"015",
    "opponent":"Trials"
  },
  {
    "name":"ChelseaK",
    "stroke":"Freestyle",
    "age":"11-12",
    "gender":"Girls",
    "date":"2003-05-10",
    "time":"30.76",
    "place":"2",
    "team":"Otters",
    "yards":50,
    "meet":"015",
    "opponent":"Trials"
  },
  {
    "name":"DeniseD",
    "stroke":"Freestyle",
    "age":"11-12",
    "gender":"Girls",
    "date":"2003-05-10",
    "time":"37.08",
    "place":"3",
    "team":"Otters",
    "yards":50,
    "meet":"015",
    "opponent":"Trials"
  },
  {
    "name":"StefaniS",
    "stroke":"Freestyle",
    "age":"11-12",
    "gender":"Girls",
    "date":"2003-05-10",
    "time":"37.49",
    "place":"4",
    "team":"Otters",
    "yards":50,
    "meet":"015",
    "opponent":"Trials"
  },
  {
    "name":"NicoleT",
    "stroke":"Freestyle",
    "age":"11-12",
    "gender":"Girls",
    "date":"2003-05-10",
    "time":"40.31",
    "place":"5",
    "team":"Otters",
    "yards":50,
    "meet":"015",
    "opponent":"Trials"
  },
  {
    "name":"CourtneyK",
    "stroke":"Freestyle",
    "age":"11-12",
    "gender":"Girls",
    "date":"2003-05-10",
    "time":"42.95",
    "place":"6",
    "team":"Otters",
    "yards":50,
    "meet":"015",
    "opponent":"Trials"
  },
  {
    "name":"MeganT",
    "stroke":"Freestyle",
    "age":"11-12",
    "gender":"Girls",
    "date":"2003-05-10",
    "time":"54.24",
    "place":"7",
    "team":"Otters",
    "yards":50,
    "meet":"015",
    "opponent":"Trials"
  },
  {
    "name":"AndreaH",
    "stroke":"Freestyle",
    "age":"11-12",
    "gender":"Girls",
    "date":"2003-05-10",
    "time":"1:00.13",
    "place":"8",
    "team":"Otters",
    "yards":50,
    "meet":"015",
    "opponent":"Trials"
  },
  {
    "name":"ChadK",
    "stroke":"Freestyle",
    "age":"13-14",
    "gender":"Boys",
    "date":"2003-05-10",
    "time":"NS",
    "place":"--",
    "team":"Otters",
    "yards":50,
    "meet":"015",
    "opponent":"Trials"
  },
  {
    "name":"RandyG",
    "stroke":"Freestyle",
    "age":"13-14",
    "gender":"Boys",
    "date":"2003-05-10",
    "time":"NS",
    "place":"--",
    "team":"Otters",
    "yards":50,
    "meet":"015",
    "opponent":"Trials"
  },
  {
    "name":"TylerT",
    "stroke":"Freestyle",
    "age":"13-14",
    "gender":"Boys",
    "date":"2003-05-10",
    "time":"NS",
    "place":"--",
    "team":"Otters",
    "yards":50,
    "meet":"015",
    "opponent":"Trials"
  },
  {
    "name":"JamesSi",
    "stroke":"Freestyle",
    "age":"13-14",
    "gender":"Boys",
    "date":"2003-05-10",
    "time":"31.38",
    "place":"1",
    "team":"Otters",
    "yards":50,
    "meet":"015",
    "opponent":"Trials"
  },
  {
    "name":"SamN",
    "stroke":"Freestyle",
    "age":"13-14",
    "gender":"Boys",
    "date":"2003-05-10",
    "time":"42.95",
    "place":"2",
    "team":"Otters",
    "yards":50,
    "meet":"015",
    "opponent":"Trials"
  },
  {
    "name":"ShainaP",
    "stroke":"Freestyle",
    "age":"13-14",
    "gender":"Girls",
    "date":"2003-05-10",
    "time":"31.18",
    "place":"1",
    "team":"Otters",
    "yards":50,
    "meet":"015",
    "opponent":"Trials"
  },
  {
    "name":"AgathaS",
    "stroke":"Freestyle",
    "age":"13-14",
    "gender":"Girls",
    "date":"2003-05-10",
    "time":"31.68",
    "place":"2",
    "team":"Otters",
    "yards":50,
    "meet":"015",
    "opponent":"Trials"
  },
  {
    "name":"BreannaS",
    "stroke":"Freestyle",
    "age":"13-14",
    "gender":"Girls",
    "date":"2003-05-10",
    "time":"32.52",
    "place":"3",
    "team":"Otters",
    "yards":50,
    "meet":"015",
    "opponent":"Trials"
  },
  {
    "name":"AnnamariaS",
    "stroke":"Freestyle",
    "age":"15-18",
    "gender":"Girls",
    "date":"2003-05-10",
    "time":"32.02",
    "place":"1",
    "team":"Otters",
    "yards":50,
    "meet":"015",
    "opponent":"Trials"
  },
  {
    "name":"JadeG",
    "stroke":"Freestyle",
    "age":"15-18",
    "gender":"Girls",
    "date":"2003-05-10",
    "time":"32.24",
    "place":"2",
    "team":"Otters",
    "yards":50,
    "meet":"015",
    "opponent":"Trials"
  },
  {
    "name":"MathewH2",
    "stroke":"Freestyle",
    "age":"6 & Under",
    "gender":"Boys",
    "date":"2003-05-10",
    "time":"21.73",
    "place":"1",
    "team":"Otters",
    "yards":25,
    "meet":"015",
    "opponent":"Trials"
  },
  {
    "name":"TylerH",
    "stroke":"Freestyle",
    "age":"6 & Under",
    "gender":"Boys",
    "date":"2003-05-10",
    "time":"27.15",
    "place":"2",
    "team":"Otters",
    "yards":25,
    "meet":"015",
    "opponent":"Trials"
  },
  {
    "name":"CoreyG",
    "stroke":"Freestyle",
    "age":"6 & Under",
    "gender":"Boys",
    "date":"2003-05-10",
    "time":"49.42",
    "place":"3",
    "team":"Otters",
    "yards":25,
    "meet":"015",
    "opponent":"Trials"
  },
  {
    "name":"JordanB",
    "stroke":"Freestyle",
    "age":"6 & Under",
    "gender":"Boys",
    "date":"2003-05-10",
    "time":"54.60",
    "place":"4",
    "team":"Otters",
    "yards":25,
    "meet":"015",
    "opponent":"Trials"
  },
  {
    "name":"MarcellaK",
    "stroke":"Freestyle",
    "age":"6 & Under",
    "gender":"Girls",
    "date":"2003-05-10",
    "time":"32.30",
    "place":"1",
    "team":"Otters",
    "yards":25,
    "meet":"015",
    "opponent":"Trials"
  },
  {
    "name":"GianaK",
    "stroke":"Freestyle",
    "age":"6 & Under",
    "gender":"Girls",
    "date":"2003-05-10",
    "time":"32.36",
    "place":"2",
    "team":"Otters",
    "yards":25,
    "meet":"015",
    "opponent":"Trials"
  },
  {
    "name":"KasscindraN",
    "stroke":"Freestyle",
    "age":"6 & Under",
    "gender":"Girls",
    "date":"2003-05-10",
    "time":"37.25",
    "place":"3",
    "team":"Otters",
    "yards":25,
    "meet":"015",
    "opponent":"Trials"
  },
  {
    "name":"AllieR",
    "stroke":"Freestyle",
    "age":"6 & Under",
    "gender":"Girls",
    "date":"2003-05-10",
    "time":"50.88",
    "place":"4",
    "team":"Otters",
    "yards":25,
    "meet":"015",
    "opponent":"Trials"
  },
  {
    "name":"EmmaD",
    "stroke":"Freestyle",
    "age":"6 & Under",
    "gender":"Girls",
    "date":"2003-05-10",
    "time":"54.16",
    "place":"5",
    "team":"Otters",
    "yards":25,
    "meet":"015",
    "opponent":"Trials"
  },
  {
    "name":"MiaB",
    "stroke":"Freestyle",
    "age":"6 & Under",
    "gender":"Girls",
    "date":"2003-05-10",
    "time":"1:03.25",
    "place":"6",
    "team":"Otters",
    "yards":25,
    "meet":"015",
    "opponent":"Trials"
  },
  {
    "name":"RebeccaM",
    "stroke":"Freestyle",
    "age":"6 & Under",
    "gender":"Girls",
    "date":"2003-05-10",
    "time":"1:36.95",
    "place":"7",
    "team":"Otters",
    "yards":25,
    "meet":"015",
    "opponent":"Trials"
  },
  {
    "name":"AlexV",
    "stroke":"Freestyle",
    "age":"7-8",
    "gender":"Boys",
    "date":"2003-05-10",
    "time":"21.92",
    "place":"1",
    "team":"Otters",
    "yards":25,
    "meet":"015",
    "opponent":"Trials"
  },
  {
    "name":"ZacharyN",
    "stroke":"Freestyle",
    "age":"7-8",
    "gender":"Boys",
    "date":"2003-05-10",
    "time":"23.68",
    "place":"2",
    "team":"Otters",
    "yards":25,
    "meet":"015",
    "opponent":"Trials"
  },
  {
    "name":"KyleM",
    "stroke":"Freestyle",
    "age":"7-8",
    "gender":"Boys",
    "date":"2003-05-10",
    "time":"25.67",
    "place":"3",
    "team":"Otters",
    "yards":25,
    "meet":"015",
    "opponent":"Trials"
  },
  {
    "name":"TheresaE",
    "stroke":"Freestyle",
    "age":"7-8",
    "gender":"Girls",
    "date":"2003-05-10",
    "time":"NS",
    "place":"--",
    "team":"Otters",
    "yards":25,
    "meet":"015",
    "opponent":"Trials"
  },
  {
    "name":"AnnaH",
    "stroke":"Freestyle",
    "age":"7-8",
    "gender":"Girls",
    "date":"2003-05-10",
    "time":"15.08",
    "place":"1",
    "team":"Otters",
    "yards":25,
    "meet":"015",
    "opponent":"Trials"
  },
  {
    "name":"JenniferR",
    "stroke":"Freestyle",
    "age":"7-8",
    "gender":"Girls",
    "date":"2003-05-10",
    "time":"22.89",
    "place":"2",
    "team":"Otters",
    "yards":25,
    "meet":"015",
    "opponent":"Trials"
  },
  {
    "name":"EmilyD1",
    "stroke":"Freestyle",
    "age":"7-8",
    "gender":"Girls",
    "date":"2003-05-10",
    "time":"23.89",
    "place":"3",
    "team":"Otters",
    "yards":25,
    "meet":"015",
    "opponent":"Trials"
  },
  {
    "name":"HayleyR",
    "stroke":"Freestyle",
    "age":"7-8",
    "gender":"Girls",
    "date":"2003-05-10",
    "time":"26.26",
    "place":"4",
    "team":"Otters",
    "yards":25,
    "meet":"015",
    "opponent":"Trials"
  },
  {
    "name":"ValerieP",
    "stroke":"Freestyle",
    "age":"7-8",
    "gender":"Girls",
    "date":"2003-05-10",
    "time":"26.32",
    "place":"5",
    "team":"Otters",
    "yards":25,
    "meet":"015",
    "opponent":"Trials"
  },
  {
    "name":"GiselleH",
    "stroke":"Freestyle",
    "age":"7-8",
    "gender":"Girls",
    "date":"2003-05-10",
    "time":"26.82",
    "place":"6",
    "team":"Otters",
    "yards":25,
    "meet":"015",
    "opponent":"Trials"
  },
  {
    "name":"SonyaS",
    "stroke":"Freestyle",
    "age":"7-8",
    "gender":"Girls",
    "date":"2003-05-10",
    "time":"31.24",
    "place":"7",
    "team":"Otters",
    "yards":25,
    "meet":"015",
    "opponent":"Trials"
  },
  {
    "name":"CaitlynB",
    "stroke":"Freestyle",
    "age":"7-8",
    "gender":"Girls",
    "date":"2003-05-10",
    "time":"31.70",
    "place":"8",
    "team":"Otters",
    "yards":25,
    "meet":"015",
    "opponent":"Trials"
  },
  {
    "name":"SereanaR",
    "stroke":"Freestyle",
    "age":"7-8",
    "gender":"Girls",
    "date":"2003-05-10",
    "time":"33.29",
    "place":"9",
    "team":"Otters",
    "yards":25,
    "meet":"015",
    "opponent":"Trials"
  },
  {
    "name":"DanteM",
    "stroke":"Freestyle",
    "age":"9-10",
    "gender":"Boys",
    "date":"2003-05-10",
    "time":"NS",
    "place":"--",
    "team":"Otters",
    "yards":25,
    "meet":"015",
    "opponent":"Trials"
  },
  {
    "name":"ErikV",
    "stroke":"Freestyle",
    "age":"9-10",
    "gender":"Boys",
    "date":"2003-05-10",
    "time":"17.80",
    "place":"1",
    "team":"Otters",
    "yards":25,
    "meet":"015",
    "opponent":"Trials"
  },
  {
    "name":"MelkiasG",
    "stroke":"Freestyle",
    "age":"9-10",
    "gender":"Boys",
    "date":"2003-05-10",
    "time":"19.36",
    "place":"2",
    "team":"Otters",
    "yards":25,
    "meet":"015",
    "opponent":"Trials"
  },
  {
    "name":"FernandoR",
    "stroke":"Freestyle",
    "age":"9-10",
    "gender":"Boys",
    "date":"2003-05-10",
    "time":"24.38",
    "place":"3",
    "team":"Otters",
    "yards":25,
    "meet":"015",
    "opponent":"Trials"
  },
  {
    "name":"AlejandroR",
    "stroke":"Freestyle",
    "age":"9-10",
    "gender":"Boys",
    "date":"2003-05-10",
    "time":"24.41",
    "place":"4",
    "team":"Otters",
    "yards":25,
    "meet":"015",
    "opponent":"Trials"
  },
  {
    "name":"AlexE",
    "stroke":"Freestyle",
    "age":"9-10",
    "gender":"Boys",
    "date":"2003-05-10",
    "time":"24.46",
    "place":"5",
    "team":"Otters",
    "yards":25,
    "meet":"015",
    "opponent":"Trials"
  },
  {
    "name":"JamesR",
    "stroke":"Freestyle",
    "age":"9-10",
    "gender":"Boys",
    "date":"2003-05-10",
    "time":"24.92",
    "place":"6",
    "team":"Otters",
    "yards":25,
    "meet":"015",
    "opponent":"Trials"
  },
  {
    "name":"ChristianH",
    "stroke":"Freestyle",
    "age":"9-10",
    "gender":"Boys",
    "date":"2003-05-10",
    "time":"32.99",
    "place":"7",
    "team":"Otters",
    "yards":25,
    "meet":"015",
    "opponent":"Trials"
  },
  {
    "name":"AndrewM",
    "stroke":"Freestyle",
    "age":"9-10",
    "gender":"Boys",
    "date":"2003-05-10",
    "time":"33.67",
    "place":"8",
    "team":"Otters",
    "yards":25,
    "meet":"015",
    "opponent":"Trials"
  },
  {
    "name":"AustinF",
    "stroke":"Freestyle",
    "age":"9-10",
    "gender":"Boys",
    "date":"2003-05-10",
    "time":"40.07",
    "place":"9",
    "team":"Otters",
    "yards":25,
    "meet":"015",
    "opponent":"Trials"
  },
  {
    "name":"ElaineH",
    "stroke":"Freestyle",
    "age":"9-10",
    "gender":"Girls",
    "date":"2003-05-10",
    "time":"14.98",
    "place":"1",
    "team":"Otters",
    "yards":25,
    "meet":"015",
    "opponent":"Trials"
  },
  {
    "name":"AishaN",
    "stroke":"Freestyle",
    "age":"9-10",
    "gender":"Girls",
    "date":"2003-05-10",
    "time":"15.47",
    "place":"2",
    "team":"Otters",
    "yards":25,
    "meet":"015",
    "opponent":"Trials"
  },
  {
    "name":"JessicaS",
    "stroke":"Freestyle",
    "age":"9-10",
    "gender":"Girls",
    "date":"2003-05-10",
    "time":"16.25",
    "place":"3",
    "team":"Otters",
    "yards":25,
    "meet":"015",
    "opponent":"Trials"
  },
  {
    "name":"CharlotteS",
    "stroke":"Freestyle",
    "age":"9-10",
    "gender":"Girls",
    "date":"2003-05-10",
    "time":"16.46",
    "place":"4",
    "team":"Otters",
    "yards":25,
    "meet":"015",
    "opponent":"Trials"
  },
  {
    "name":"JamieG",
    "stroke":"Freestyle",
    "age":"9-10",
    "gender":"Girls",
    "date":"2003-05-10",
    "time":"19.80",
    "place":"5",
    "team":"Otters",
    "yards":25,
    "meet":"015",
    "opponent":"Trials"
  },
  {
    "name":"TaylorR",
    "stroke":"Freestyle",
    "age":"9-10",
    "gender":"Girls",
    "date":"2003-05-10",
    "time":"24.65",
    "place":"6",
    "team":"Otters",
    "yards":25,
    "meet":"015",
    "opponent":"Trials"
  },
  {
    "name":"GabrielleC",
    "stroke":"Freestyle",
    "age":"9-10",
    "gender":"Girls",
    "date":"2003-05-10",
    "time":"26.22",
    "place":"7",
    "team":"Otters",
    "yards":25,
    "meet":"015",
    "opponent":"Trials"
  }
]}


