
{"scores":[
  {
    "name":"RachelM",
    "stroke":"Back",
    "age":"15-18",
    "gender":"Girls",
    "date":"2014-05-17",
    "time":"50.52",
    "place":"16",
    "team":"Otters",
    "yards":50,
    "meet":"093",
    "opponent":"Trials"
  },
  {
    "name":"RachelM",
    "stroke":"Back",
    "age":"15-18",
    "gender":"Girls",
    "date":"2014-06-14",
    "time":"48.19",
    "place":"12",
    "team":"Otters",
    "yards":50,
    "meet":"096",
    "opponent":"Pinehurst"
  },
  {
    "name":"RachelM",
    "stroke":"Back",
    "age":"15-18",
    "gender":"Girls",
    "date":"2014-06-21",
    "time":"47.50",
    "place":"22",
    "team":"Otters",
    "yards":50,
    "meet":"097",
    "opponent":"Crossgate"
  },
  {
    "name":"RachelM",
    "stroke":"Back",
    "age":"15-18",
    "gender":"Girls",
    "date":"2014-06-28",
    "time":"48.97",
    "place":"13",
    "team":"Otters",
    "yards":50,
    "meet":"098",
    "opponent":"Almaden"
  },
  {
    "name":"RachelM",
    "stroke":"Back",
    "age":"15-18",
    "gender":"Girls",
    "date":"2014-07-12",
    "time":"DQ",
    "place":"--",
    "team":"Otters",
    "yards":50,
    "meet":"099",
    "opponent":"Champs"
  },
  {
    "name":"RachelM",
    "stroke":"Breast",
    "age":"15-18",
    "gender":"Girls",
    "date":"2014-05-17",
    "time":"53.13",
    "place":"14",
    "team":"Otters",
    "yards":50,
    "meet":"093",
    "opponent":"Trials"
  },
  {
    "name":"RachelM",
    "stroke":"Breast",
    "age":"15-18",
    "gender":"Girls",
    "date":"2014-06-14",
    "time":"47.71",
    "place":"11",
    "team":"Otters",
    "yards":50,
    "meet":"096",
    "opponent":"Pinehurst"
  },
  {
    "name":"RachelM",
    "stroke":"Breast",
    "age":"15-18",
    "gender":"Girls",
    "date":"2014-06-28",
    "time":"47.68",
    "place":"14",
    "team":"Otters",
    "yards":50,
    "meet":"098",
    "opponent":"Almaden"
  },
  {
    "name":"RachelM",
    "stroke":"Breast",
    "age":"15-18",
    "gender":"Girls",
    "date":"2014-07-12",
    "time":"50.20",
    "place":"33",
    "team":"Otters",
    "yards":50,
    "meet":"099",
    "opponent":"Champs"
  },
  {
    "name":"RachelM",
    "stroke":"Butterfly",
    "age":"15-18",
    "gender":"Girls",
    "date":"2014-05-17",
    "time":"55.86",
    "place":"11",
    "team":"Otters",
    "yards":50,
    "meet":"093",
    "opponent":"Trials"
  },
  {
    "name":"RachelM",
    "stroke":"Freestyle",
    "age":"15-18",
    "gender":"Girls",
    "date":"2014-05-17",
    "time":"45.45",
    "place":"16",
    "team":"Otters",
    "yards":50,
    "meet":"093",
    "opponent":"Trials"
  },
  {
    "name":"RachelM",
    "stroke":"Freestyle",
    "age":"15-18",
    "gender":"Girls",
    "date":"2014-06-14",
    "time":"40.60",
    "place":"16",
    "team":"Otters",
    "yards":50,
    "meet":"096",
    "opponent":"Pinehurst"
  },
  {
    "name":"RachelM",
    "stroke":"Freestyle",
    "age":"15-18",
    "gender":"Girls",
    "date":"2014-06-21",
    "time":"45.10",
    "place":"30",
    "team":"Otters",
    "yards":50,
    "meet":"097",
    "opponent":"Crossgate"
  },
  {
    "name":"RachelM",
    "stroke":"Freestyle",
    "age":"15-18",
    "gender":"Girls",
    "date":"2014-06-28",
    "time":"40.43",
    "place":"21",
    "team":"Otters",
    "yards":50,
    "meet":"098",
    "opponent":"Almaden"
  },
  {
    "name":"RachelM",
    "stroke":"Freestyle",
    "age":"15-18",
    "gender":"Girls",
    "date":"2014-07-12",
    "time":"41.39",
    "place":"68",
    "team":"Otters",
    "yards":50,
    "meet":"099",
    "opponent":"Champs"
  }
]}


