
{"scores":[
  {
    "name":"SarahH",
    "stroke":"Back",
    "age":"11-12",
    "gender":"Girls",
    "date":"2005-06-04",
    "time":"1:08.03",
    "place":"11",
    "team":"Otters",
    "yards":50,
    "meet":"031",
    "opponent":"Almaden"
  },
  {
    "name":"SarahH",
    "stroke":"Back",
    "age":"11-12",
    "gender":"Girls",
    "date":"2005-06-11",
    "time":"1:06.56",
    "place":"16",
    "team":"Otters",
    "yards":50,
    "meet":"032",
    "opponent":"Creekside"
  },
  {
    "name":"SarahH",
    "stroke":"Back",
    "age":"11-12",
    "gender":"Girls",
    "date":"2005-06-18",
    "time":"DQ",
    "place":"--",
    "team":"Otters",
    "yards":50,
    "meet":"033",
    "opponent":"Shadowbrook"
  },
  {
    "name":"SarahH",
    "stroke":"Back",
    "age":"11-12",
    "gender":"Girls",
    "date":"2005-06-25",
    "time":"1:08.97",
    "place":"16",
    "team":"Otters",
    "yards":50,
    "meet":"034",
    "opponent":"Pinehurst"
  },
  {
    "name":"SarahH",
    "stroke":"Back",
    "age":"11-12",
    "gender":"Girls",
    "date":"2005-07-16",
    "time":"1:08.95",
    "place":"45",
    "team":"Otters",
    "yards":50,
    "meet":"036",
    "opponent":"Champs"
  },
  {
    "name":"SarahH",
    "stroke":"Back",
    "age":"11-12",
    "gender":"Girls",
    "date":"2006-05-20",
    "time":"1:10.90",
    "place":"18",
    "team":"Otters",
    "yards":50,
    "meet":"037",
    "opponent":"Trials"
  },
  {
    "name":"SarahH",
    "stroke":"Back",
    "age":"11-12",
    "gender":"Girls",
    "date":"2006-06-17",
    "time":"1:05.37",
    "place":"21",
    "team":"Otters",
    "yards":50,
    "meet":"040",
    "opponent":"Creekside"
  },
  {
    "name":"SarahH",
    "stroke":"Back",
    "age":"11-12",
    "gender":"Girls",
    "date":"2006-06-24",
    "time":"1:05.82",
    "place":"13",
    "team":"Otters",
    "yards":50,
    "meet":"041",
    "opponent":"Shadowbrook"
  },
  {
    "name":"SarahH",
    "stroke":"Back",
    "age":"11-12",
    "gender":"Girls",
    "date":"2006-07-08",
    "time":"1:05.94",
    "place":"9",
    "team":"Otters",
    "yards":50,
    "meet":"042",
    "opponent":"Pinehurst"
  },
  {
    "name":"SarahH",
    "stroke":"Back",
    "age":"11-12",
    "gender":"Girls",
    "date":"2006-07-15",
    "time":"1:03.21",
    "place":"46",
    "team":"Otters",
    "yards":50,
    "meet":"043",
    "opponent":"Champs"
  },
  {
    "name":"SarahH",
    "stroke":"Back",
    "age":"9-10",
    "gender":"Girls",
    "date":"2004-05-20",
    "time":"52.66",
    "place":"18",
    "team":"Otters",
    "yards":25,
    "meet":"023",
    "opponent":"Trials"
  },
  {
    "name":"SarahH",
    "stroke":"Back",
    "age":"9-10",
    "gender":"Girls",
    "date":"2004-06-05",
    "time":"38.84",
    "place":"22",
    "team":"Otters",
    "yards":25,
    "meet":"024",
    "opponent":"Creekside"
  },
  {
    "name":"SarahH",
    "stroke":"Back",
    "age":"9-10",
    "gender":"Girls",
    "date":"2004-06-12",
    "time":"33.39",
    "place":"16",
    "team":"Otters",
    "yards":25,
    "meet":"025",
    "opponent":"Shadowbrook"
  },
  {
    "name":"SarahH",
    "stroke":"Back",
    "age":"9-10",
    "gender":"Girls",
    "date":"2004-06-19",
    "time":"33.15",
    "place":"18",
    "team":"Otters",
    "yards":25,
    "meet":"026",
    "opponent":"Pinehurst"
  },
  {
    "name":"SarahH",
    "stroke":"Back",
    "age":"9-10",
    "gender":"Girls",
    "date":"2004-06-26",
    "time":"29.88",
    "place":"17",
    "team":"Otters",
    "yards":25,
    "meet":"027",
    "opponent":"Crossgate"
  },
  {
    "name":"SarahH",
    "stroke":"Back",
    "age":"9-10",
    "gender":"Girls",
    "date":"2004-07-10",
    "time":"30.22",
    "place":"14",
    "team":"Otters",
    "yards":25,
    "meet":"028",
    "opponent":"Almaden"
  },
  {
    "name":"SarahH",
    "stroke":"Back",
    "age":"9-10",
    "gender":"Girls",
    "date":"2004-07-17",
    "time":"32.49",
    "place":"54",
    "team":"Otters",
    "yards":25,
    "meet":"029",
    "opponent":"Champs"
  },
  {
    "name":"SarahH",
    "stroke":"Breast",
    "age":"11-12",
    "gender":"Girls",
    "date":"2005-06-04",
    "time":"1:12.59",
    "place":"17",
    "team":"Otters",
    "yards":50,
    "meet":"031",
    "opponent":"Almaden"
  },
  {
    "name":"SarahH",
    "stroke":"Breast",
    "age":"11-12",
    "gender":"Girls",
    "date":"2005-06-11",
    "time":"1:05.25",
    "place":"15",
    "team":"Otters",
    "yards":50,
    "meet":"032",
    "opponent":"Creekside"
  },
  {
    "name":"SarahH",
    "stroke":"Breast",
    "age":"11-12",
    "gender":"Girls",
    "date":"2005-06-18",
    "time":"1:02.87",
    "place":"8",
    "team":"Otters",
    "yards":50,
    "meet":"033",
    "opponent":"Shadowbrook"
  },
  {
    "name":"SarahH",
    "stroke":"Breast",
    "age":"11-12",
    "gender":"Girls",
    "date":"2005-06-25",
    "time":"1:04.37",
    "place":"12",
    "team":"Otters",
    "yards":50,
    "meet":"034",
    "opponent":"Pinehurst"
  },
  {
    "name":"SarahH",
    "stroke":"Breast",
    "age":"11-12",
    "gender":"Girls",
    "date":"2005-07-16",
    "time":"58.84",
    "place":"41",
    "team":"Otters",
    "yards":50,
    "meet":"036",
    "opponent":"Champs"
  },
  {
    "name":"SarahH",
    "stroke":"Breast",
    "age":"11-12",
    "gender":"Girls",
    "date":"2006-05-20",
    "time":"1:05.22",
    "place":"14",
    "team":"Otters",
    "yards":50,
    "meet":"037",
    "opponent":"Trials"
  },
  {
    "name":"SarahH",
    "stroke":"Breast",
    "age":"11-12",
    "gender":"Girls",
    "date":"2006-06-17",
    "time":"1:00.36",
    "place":"12",
    "team":"Otters",
    "yards":50,
    "meet":"040",
    "opponent":"Creekside"
  },
  {
    "name":"SarahH",
    "stroke":"Breast",
    "age":"11-12",
    "gender":"Girls",
    "date":"2006-06-24",
    "time":"58.57",
    "place":"10",
    "team":"Otters",
    "yards":50,
    "meet":"041",
    "opponent":"Shadowbrook"
  },
  {
    "name":"SarahH",
    "stroke":"Breast",
    "age":"11-12",
    "gender":"Girls",
    "date":"2006-07-08",
    "time":"1:03.40",
    "place":"16",
    "team":"Otters",
    "yards":50,
    "meet":"042",
    "opponent":"Pinehurst"
  },
  {
    "name":"SarahH",
    "stroke":"Breast",
    "age":"11-12",
    "gender":"Girls",
    "date":"2006-07-15",
    "time":"1:05.46",
    "place":"47",
    "team":"Otters",
    "yards":50,
    "meet":"043",
    "opponent":"Champs"
  },
  {
    "name":"SarahH",
    "stroke":"Breast",
    "age":"9-10",
    "gender":"Girls",
    "date":"2004-05-20",
    "time":"51.18",
    "place":"14",
    "team":"Otters",
    "yards":25,
    "meet":"023",
    "opponent":"Trials"
  },
  {
    "name":"SarahH",
    "stroke":"Breast",
    "age":"9-10",
    "gender":"Girls",
    "date":"2004-06-05",
    "time":"45.38",
    "place":"14",
    "team":"Otters",
    "yards":25,
    "meet":"024",
    "opponent":"Creekside"
  },
  {
    "name":"SarahH",
    "stroke":"Breast",
    "age":"9-10",
    "gender":"Girls",
    "date":"2004-06-12",
    "time":"41.55",
    "place":"13",
    "team":"Otters",
    "yards":25,
    "meet":"025",
    "opponent":"Shadowbrook"
  },
  {
    "name":"SarahH",
    "stroke":"Breast",
    "age":"9-10",
    "gender":"Girls",
    "date":"2004-06-19",
    "time":"40.67",
    "place":"13",
    "team":"Otters",
    "yards":25,
    "meet":"026",
    "opponent":"Pinehurst"
  },
  {
    "name":"SarahH",
    "stroke":"Breast",
    "age":"9-10",
    "gender":"Girls",
    "date":"2004-06-26",
    "time":"47.51",
    "place":"10",
    "team":"Otters",
    "yards":25,
    "meet":"027",
    "opponent":"Crossgate"
  },
  {
    "name":"SarahH",
    "stroke":"Breast",
    "age":"9-10",
    "gender":"Girls",
    "date":"2004-07-10",
    "time":"38.47",
    "place":"14",
    "team":"Otters",
    "yards":25,
    "meet":"028",
    "opponent":"Almaden"
  },
  {
    "name":"SarahH",
    "stroke":"Breast",
    "age":"9-10",
    "gender":"Girls",
    "date":"2004-07-17",
    "time":"37.32",
    "place":"35",
    "team":"Otters",
    "yards":25,
    "meet":"029",
    "opponent":"Champs"
  },
  {
    "name":"SarahH",
    "stroke":"Butterfly",
    "age":"11-12",
    "gender":"Girls",
    "date":"2006-05-20",
    "time":"1:15.87",
    "place":"18",
    "team":"Otters",
    "yards":50,
    "meet":"037",
    "opponent":"Trials"
  },
  {
    "name":"SarahH",
    "stroke":"Butterfly",
    "age":"9-10",
    "gender":"Girls",
    "date":"2004-05-20",
    "time":"43.30",
    "place":"18",
    "team":"Otters",
    "yards":25,
    "meet":"023",
    "opponent":"Trials"
  },
  {
    "name":"SarahH",
    "stroke":"Freestyle Relay",
    "age":"9-10",
    "gender":"Girls",
    "date":"2004-06-26",
    "time":"X1:24.46",
    "place":"--",
    "team":"Otters",
    "yards":100,
    "meet":"027",
    "opponent":"Crossgate"
  },
  {
    "name":"SarahH",
    "stroke":"Freestyle",
    "age":"11-12",
    "gender":"Girls",
    "date":"2005-06-04",
    "time":"55.48",
    "place":"21",
    "team":"Otters",
    "yards":50,
    "meet":"031",
    "opponent":"Almaden"
  },
  {
    "name":"SarahH",
    "stroke":"Freestyle",
    "age":"11-12",
    "gender":"Girls",
    "date":"2005-06-11",
    "time":"48.50",
    "place":"19",
    "team":"Otters",
    "yards":50,
    "meet":"032",
    "opponent":"Creekside"
  },
  {
    "name":"SarahH",
    "stroke":"Freestyle",
    "age":"11-12",
    "gender":"Girls",
    "date":"2005-06-18",
    "time":"48.85",
    "place":"11",
    "team":"Otters",
    "yards":50,
    "meet":"033",
    "opponent":"Shadowbrook"
  },
  {
    "name":"SarahH",
    "stroke":"Freestyle",
    "age":"11-12",
    "gender":"Girls",
    "date":"2005-06-25",
    "time":"51.40",
    "place":"19",
    "team":"Otters",
    "yards":50,
    "meet":"034",
    "opponent":"Pinehurst"
  },
  {
    "name":"SarahH",
    "stroke":"Freestyle",
    "age":"11-12",
    "gender":"Girls",
    "date":"2005-07-16",
    "time":"55.03",
    "place":"64",
    "team":"Otters",
    "yards":50,
    "meet":"036",
    "opponent":"Champs"
  },
  {
    "name":"SarahH",
    "stroke":"Freestyle",
    "age":"11-12",
    "gender":"Girls",
    "date":"2006-05-20",
    "time":"45.00",
    "place":"18",
    "team":"Otters",
    "yards":50,
    "meet":"037",
    "opponent":"Trials"
  },
  {
    "name":"SarahH",
    "stroke":"Freestyle",
    "age":"11-12",
    "gender":"Girls",
    "date":"2006-06-17",
    "time":"45.76",
    "place":"23",
    "team":"Otters",
    "yards":50,
    "meet":"040",
    "opponent":"Creekside"
  },
  {
    "name":"SarahH",
    "stroke":"Freestyle",
    "age":"11-12",
    "gender":"Girls",
    "date":"2006-06-24",
    "time":"49.19",
    "place":"17",
    "team":"Otters",
    "yards":50,
    "meet":"041",
    "opponent":"Shadowbrook"
  },
  {
    "name":"SarahH",
    "stroke":"Freestyle",
    "age":"11-12",
    "gender":"Girls",
    "date":"2006-07-08",
    "time":"52.36",
    "place":"21",
    "team":"Otters",
    "yards":50,
    "meet":"042",
    "opponent":"Pinehurst"
  },
  {
    "name":"SarahH",
    "stroke":"Freestyle",
    "age":"11-12",
    "gender":"Girls",
    "date":"2006-07-15",
    "time":"48.14",
    "place":"67",
    "team":"Otters",
    "yards":50,
    "meet":"043",
    "opponent":"Champs"
  },
  {
    "name":"SarahH",
    "stroke":"Freestyle",
    "age":"9-10",
    "gender":"Girls",
    "date":"2004-05-20",
    "time":"27.52",
    "place":"14",
    "team":"Otters",
    "yards":25,
    "meet":"023",
    "opponent":"Trials"
  },
  {
    "name":"SarahH",
    "stroke":"Freestyle",
    "age":"9-10",
    "gender":"Girls",
    "date":"2004-06-05",
    "time":"28.07",
    "place":"24",
    "team":"Otters",
    "yards":25,
    "meet":"024",
    "opponent":"Creekside"
  },
  {
    "name":"SarahH",
    "stroke":"Freestyle",
    "age":"9-10",
    "gender":"Girls",
    "date":"2004-06-12",
    "time":"29.69",
    "place":"17",
    "team":"Otters",
    "yards":25,
    "meet":"025",
    "opponent":"Shadowbrook"
  },
  {
    "name":"SarahH",
    "stroke":"Freestyle",
    "age":"9-10",
    "gender":"Girls",
    "date":"2004-06-19",
    "time":"27.03",
    "place":"16",
    "team":"Otters",
    "yards":25,
    "meet":"026",
    "opponent":"Pinehurst"
  },
  {
    "name":"SarahH",
    "stroke":"Freestyle",
    "age":"9-10",
    "gender":"Girls",
    "date":"2004-06-26",
    "time":"23.94",
    "place":"18",
    "team":"Otters",
    "yards":25,
    "meet":"027",
    "opponent":"Crossgate"
  },
  {
    "name":"SarahH",
    "stroke":"Freestyle",
    "age":"9-10",
    "gender":"Girls",
    "date":"2004-07-10",
    "time":"22.65",
    "place":"17",
    "team":"Otters",
    "yards":25,
    "meet":"028",
    "opponent":"Almaden"
  },
  {
    "name":"SarahH",
    "stroke":"Freestyle",
    "age":"9-10",
    "gender":"Girls",
    "date":"2004-07-17",
    "time":"23.69",
    "place":"65",
    "team":"Otters",
    "yards":25,
    "meet":"029",
    "opponent":"Champs"
  }
]}


