
{"scores":[
  {
    "name":"YeseniaV",
    "stroke":"Back",
    "age":"15-18",
    "gender":"Girls",
    "date":"2014-05-17",
    "time":"48.70",
    "place":"15",
    "team":"Otters",
    "yards":50,
    "meet":"093",
    "opponent":"Trials"
  },
  {
    "name":"YeseniaV",
    "stroke":"Back",
    "age":"15-18",
    "gender":"Girls",
    "date":"2014-06-07",
    "time":"48.35",
    "place":"12",
    "team":"Otters",
    "yards":50,
    "meet":"095",
    "opponent":"Shadowbrook"
  },
  {
    "name":"YeseniaV",
    "stroke":"Back",
    "age":"15-18",
    "gender":"Girls",
    "date":"2014-06-28",
    "time":"DQ",
    "place":"--",
    "team":"Otters",
    "yards":50,
    "meet":"098",
    "opponent":"Almaden"
  },
  {
    "name":"YeseniaV",
    "stroke":"Back",
    "age":"15-18",
    "gender":"Girls",
    "date":"2014-07-12",
    "time":"49.17",
    "place":"50",
    "team":"Otters",
    "yards":50,
    "meet":"099",
    "opponent":"Champs"
  },
  {
    "name":"YeseniaV",
    "stroke":"Breast",
    "age":"15-18",
    "gender":"Girls",
    "date":"2014-05-17",
    "time":"50.67",
    "place":"13",
    "team":"Otters",
    "yards":50,
    "meet":"093",
    "opponent":"Trials"
  },
  {
    "name":"YeseniaV",
    "stroke":"Breast",
    "age":"15-18",
    "gender":"Girls",
    "date":"2014-06-07",
    "time":"50.88",
    "place":"15",
    "team":"Otters",
    "yards":50,
    "meet":"095",
    "opponent":"Shadowbrook"
  },
  {
    "name":"YeseniaV",
    "stroke":"Butterfly",
    "age":"15-18",
    "gender":"Girls",
    "date":"2014-05-17",
    "time":"57.58",
    "place":"12",
    "team":"Otters",
    "yards":50,
    "meet":"093",
    "opponent":"Trials"
  },
  {
    "name":"YeseniaV",
    "stroke":"Freestyle",
    "age":"15-18",
    "gender":"Girls",
    "date":"2014-05-17",
    "time":"40.99",
    "place":"14",
    "team":"Otters",
    "yards":50,
    "meet":"093",
    "opponent":"Trials"
  },
  {
    "name":"YeseniaV",
    "stroke":"Freestyle",
    "age":"15-18",
    "gender":"Girls",
    "date":"2014-06-07",
    "time":"41.27",
    "place":"23",
    "team":"Otters",
    "yards":50,
    "meet":"095",
    "opponent":"Shadowbrook"
  },
  {
    "name":"YeseniaV",
    "stroke":"Freestyle",
    "age":"15-18",
    "gender":"Girls",
    "date":"2014-06-28",
    "time":"40.57",
    "place":"22",
    "team":"Otters",
    "yards":50,
    "meet":"098",
    "opponent":"Almaden"
  },
  {
    "name":"YeseniaV",
    "stroke":"Freestyle",
    "age":"15-18",
    "gender":"Girls",
    "date":"2014-07-12",
    "time":"37.96",
    "place":"67",
    "team":"Otters",
    "yards":50,
    "meet":"099",
    "opponent":"Champs"
  }
]}


